Workbook

Sheet Start Here
A1: CLIMATE-RESILIENT TREE REMOVAL AND REPLACEMENT — START HERE
A2: A planning and record-keeping tool for replacing high-maintenance plantings with climate-adapted species in the southern Willamette Valley, Oregon. It suits arborists, landscape managers, public agencies and property owners. Use the workflows below. Each step names the tab to open.
A4: SETTINGS — change these here only
A5: Setting | B5: Value | C5: Used by
A6: Labor rate ($/hour) | B6: 150 | C6: Conversion Economics, Establishment Water. Placeholder: enter your own rate.
A7: Planning horizon (years) | B7: 15 | C7: Conversion Economics. Use the number of years you expect to manage the site.
A8: Dry season length (days) | B8: 122 | C8: Establishment Water, Watering Plan. June 15 to October 15.
A9: Tier B cap (share of plants per install) | B9: 0.1 | C9: Planting plans, Program Review.
A10: Minimum plants before diversity flags count | B10: 30 | C10: Program Review. Below this number the flags show 'too few plants'.
A12: TABS — WHAT EACH ONE IS FOR
A13: Tab | B13: Group | C13: Use it to
A14: Field Card | B14: Field | C14: Record a site assessment. Print it. Carry it.
A15: Conversion Crosswalk | B15: Plan | C15: Find what replaces a legacy plant, and why.
A16: Ash EAB | B16: Plan | C16: EAB status, treatment costs, decision rules, phased replacement, quarantine and safety.
A17: Palette | B17: Plan | C17: Choose species by soil group, size, tier and water class.
A18: Hedgerow Design | B18: Plan | C18: Design a mixed hedgerow and count the plants.
A19: Establishment Water | B19: Plan | C19: Calculate the 3-year watering plan and its cost for one site.
A20: Watering Plan | B20: Plan | C20: Print the watering schedule for whoever waters. It fills from Establishment Water.
A21: Conversion Economics | B21: Plan | C21: Compare the cost of the old planting with the conversion.
A22: Install Log | B22: Records | C22: Record every install. Score condition at each visit.
A23: Ash Register | B23: Records | C23: Record every ash tree. Recommendation, costs and next treatment fill in.
A24: Program Review | B24: Records | C24: Check survival and diversity once a year. Updates by itself.
A25: Reference | B25: Reference | C25: Tier rules, soil groups, water classes, palette summary and sources.
A27: W1. ASSESS A SITE
A28: Step 1 | B28: Open a blank Field Card. It takes about 4 minutes.
A29: Step 2 | B29: Name the legacy plant and the scope (length, width or stem count).
A30: Step 3 | B30: Call the soil group. If you are not sure, dig 18 in and fill the hole with water. If it has not drained in 1 hour, call it Group 1.
A31: Step 4 | B31: Mark the class: Remove soon (failing or hazardous) or Optional (healthy but costly to keep).
A32: Step 5 | B32: Take photos. File the card.
B33: RULE: Recommend a replacement only where the plant needs it. Otherwise note the condition and move on.
A35: W2. SET PRIORITIES — once a month
A36: Step 1 | B36: Act on Remove soon cards first. These plants are failing or hazardous.
A37: Step 2 | B37: Hold Optional cards. They pay back best where the site will be managed for 10 years or more.
A38: Step 3 | B38: Keep all other cards on file as observed conditions. Check them at the next visit.
A40: W3. PLAN A REPLACEMENT
A41: Step 1 | B41: Conversion Crosswalk: find the legacy plant. Read the soil notes and the considerations. For ash, go to workflow W8 instead.
A42: Step 2 | B42: Palette: filter the site's soil group column to 'Yes'. Check Tier, Max Ht, Under Wires, Water Class and Review By.
A43: Step 3 | B43: If the hedge site is 8 ft wide or more, offer a hedgerow. Use Hedgerow Design for the mix and the plant count.
A44: Step 4 | B44: Establishment Water: enter the soil group and each plant line. Note the 3-year watering cost if the watering is hired out.
A45: Step 5 | B45: Conversion Economics: enter the site numbers in the matching column. Use the cost curve for Optional replacements. Use the cost-of-waiting line for Remove soon replacements.
A46: Step 6 | B46: Check the limits: Tier B plants are 10% or less of the planting. Rose family is 30% or less of a hedgerow. Drought-adapted plants never go on shared irrigation.
A47: Step 7 | B47: Decide who waters: the owner or a contractor. Write it down. A replacement guarantee usually depends on it.
A49: W4. INSTALL DAY
A50: Step 1 | B50: Install Log: add one row per species. Pick the species from the dropdown.
A51: Step 2 | B51: Enter Qty Alive the same as Qty Planted.
A52: Step 3 | B52: Check that the Tier column fills in. If it shows 'NOT IN PALETTE', fix the species name.
A53: Step 4 | B53: Watering Plan: enter the owner, address, install date and who waters. Print it. Give it to whoever waters.
A54: Step 5 | B54: If a contractor waters, put each watering visit on the schedule.
A55: Step 6 | B55: Record the GIS point ID.
A57: W5. MAINTENANCE VISIT
A58: Step 1 | B58: Install Log: filter or sort by Next Score Due. Red dates are overdue.
A59: Step 2 | B59: Score each row 1 to 5 in the matching year column. Update Qty Alive.
A60: Step 3 | B60: If plants died, choose a Failure Cause. Transplant shock in year 1 is not a species failure.
A61: Step 4 | B61: Replace failed plants under a guarantee only if the water plan was followed.
A63: W6. ANNUAL REVIEW — each August, before fall orders
A64: Step 1 | B64: Program Review: read survival by soil group and by tier.
A65: Step 2 | B65: Read the diversity flags. They count only after the minimum plant number in Settings.
A66: Step 3 | B66: Promote a Tier B species to A after 3 or more installs reach year 3 with 80% or more survival.
A67: Step 4 | B67: Demote a species with less than 70% survival. Do not count mower damage or a missed water plan.
A68: Step 5 | B68: Palette: sort by Review By. Act on any date that has passed.
A69: Step 6 | B69: Replace the placeholder numbers listed below with local figures as records build up.
A71: W7. ADD A SPECIES
A72: Step 1 | B72: Screen it on both axes: summer drought and winter-wet clay. Check it against local invasive plant lists (in Eugene, the city Native and Non-Native Plant List).
A73: Step 2 | B73: Add a row at the bottom of the Palette. Fill every column, including Genus, Family, Water Class and Source.
A74: Step 3 | B74: Start it at Tier B.
A75: Step 4 | B75: The Install Log dropdown and Program Review pick it up by themselves (up to 150 species).
A77: W8. ASH TREES (EAB)
A78: Step 1 | B78: For each ash tree, fill the ash fields on a Field Card: DBH, canopy dieback, EAB signs, value, site type and target.
A79: Step 2 | B79: Ash Register: add one row per tree. The recommendation, replacement and costs fill in.
A80: Step 3 | B80: Read the ash considerations in the Crosswalk. Treat healthy, high-value trees. Plant successors for the rest.
A81: Step 4 | B81: If treated, enter the date in Last Treated. Put Next Treatment Due on the schedule.
A82: Step 5 | B82: If a successor is planted, add it to the Install Log. Copy its Install ID into the register.
A83: Step 6 | B83: Suspected EAB in Lane County: report it to the Oregon Invasive Species Hotline. Do not move the wood.
A84: Step 7 | B84: Every 3 months, check EAB status and update the date on the Ash EAB tab.
A86: OPEN ITEMS — placeholder numbers to replace with local data
A87: 1. | B87: Conversion Economics: shearing hours per visit, removal hours, stock costs, emergency removal costs. All blue cells there are estimates.
A88: 2. | B88: Establishment Water: labor hours per watering visit, and the interval table. Check soil moisture at 6 to 8 in with a probe on the first plantings.
A89: 3. | B89: Palette: sourcing ratings. Add grower names and lead times before the first order.
A90: 4. | B90: Tolerance ratings and tiers are professional judgment, not trial data. The Install Log will correct them over time.
A91: 5. | B91: Ash EAB: injection cost, planned removal cost, emergency multiplier and replacement cost. Also check EAB status every 3 months.
A93: CELL CONVENTIONS
A94: Yellow cell, blue text | B94: You type here.
A95: Black text | B95: Formula. Do not type over it.
A96: Tab colors | B96: Dark green = start. Green = field. Blue = planning. Orange = records. Grey = reference.
A97: Dropdowns | B97: Most input columns have dropdowns. A warning appears if you type a value that is not on the list.

Sheet Field Card
A1: CONVERSION FIELD CARD
A2: Fill on site. Create an Install Log or Ash Register row after the visit.
A3: Owner | C3: Date
A4: Address | C4: Assessed by
A5: THE PLANT
A6: Legacy plant | B6: laurel / boxwood / arborvitae / photinia / birch / pear / plum / ash | C6: Scope | D6: length and width (ft), or stem count
A7: Class | B7: REMOVE SOON / OPTIONAL / PLAN SUCCESSION | C7: Condition | D7: good / fair / poor / failing
A8: THE SITE
A9: Soil group | B9: 1 / 2 / 3 (see below) | C9: Aspect | D9: N NE E SE S SW W NW
A10: Water access | B10: irrigated? / hose bib distance | C10: Overhead wires | D10: Y / N
A11: Rooting volume | B11: open / restricted / severe | C11: Deer pressure | D11: none / moderate / heavy
A12: ASH ONLY — one card per ash tree
A13: DBH (in) | C13: Canopy dieback % | D13: estimate, top down
A14: EAB signs | B14: D-holes / woodpecker / splits / sprouts / none | C14: Near target | D14: house / road / play area / none
A15: Tree value | B15: high / medium / low | C15: Site type | D15: upland / wet / riparian
A16: THE CALL
A17: Recommended replacement | B17: from the quick reference below; ash: Ash Register decides
A18: Owner interest | B18: high / some / none | C18: Photos taken | D18: Y / N
A19: Follow-up action | B19: plan replacement / revisit / no action / add to phased plan
A20: Notes
A22: QUICK REFERENCE
A23: Legacy plant | B23: Primary replacement | C23: Class | D23: Note
A24: English laurel | B24: Pacific wax myrtle | C24: Optional | D24: Maintenance cost; city-listed invasive
A25: Boxwood | B25: Osmanthus delavayi | C25: Optional | D25: Best payback; blight risk
A26: Arborvitae | B26: Incense cedar | C26: Remove soon | D26: Not western redcedar
A27: Photinia | B27: Osmanthus x burkwoodii | C27: Remove soon | D27: Ends a recurring failure
A28: Birch | B28: Parrotia persica | C28: Remove soon | D28: No white-bark equivalent
A29: Bradford pear | B29: Parrotia persica | C29: Remove soon | D29: Plan removal before failure
A30: Flowering plum | B30: Cotinus 'Royal Purple' | C30: Remove soon | D30: Keeps purple foliage
A31: Ash (EAB) | B31: Treat, plant first, or replace | C31: Plan succession | D31: Use the Ash EAB tab
A32: Any hedge 8+ ft wide | B32: Mixed hedgerow | C32: — | D32: See Hedgerow Design tab
A34: SOIL GROUP — FIELD CALL
A35: Group 1 | B35: Valley bottom clay. Sticky when wet, cracks when dry. Mottled or grey-green at depth. Standing water in winter.
A36: Group 2 | B36: Alluvial silt loam. Dark, crumbly, drains freely, no mottling. Floodplain and low terrace.
A37: Group 3 | B37: Footslope or upland red clay. Reddish, on a slope, sheds water, moderately deep (Nekia, Bellpine, Dixonville) to very deep (Jory) over bedrock. Dry in summer.
A38: If unsure | B38: Dig 18 in. Fill with water. Not drained in 1 hour = Group 1, whatever the soil survey says.
A40: Remove soon = failing or hazardous: plan around timing and risk. Optional = healthy but costly to keep: compare the 15-year cost. Plan succession = healthy ash before EAB arrives: treat, or plant a successor first. Suspected EAB in Lane County: report it; do not move the wood.

Sheet Conversion Crosswalk
A1: Legacy Plant | B1: Typical Form | C1: Class | D1: Why It Costs / Fails | E1: Primary Replacement | F1: Alternates | G1: Soil Group Notes | H1: Maintenance Delta | I1: Considerations
A2: Prunus laurocerasus | B2: English laurel hedge | C2: Optional | D2: Grows 2-3 ft a year, so it is sheared 2-3 times a year for as long as it stands. Shot hole fungus in wet springs. The City of Eugene lists it as invasive: birds carry the seed into forest understory. | E2: Morella californica (Pacific wax myrtle) | F2: Osmanthus x burkwoodii (formal); Calocedrus decurrens (tall screen); Frangula californica 'Eve Case' (medium) | G2: Wax myrtle works on all three groups. Osmanthus and Frangula want drainage - berm on Group 1. | H2: 2-3 shearings/yr down to 1 | I2: It is healthy, so the reason to replace it is cost and spread. Over 15 years, shearing costs more than the conversion. The City of Eugene lists it as invasive: birds carry its seed into nearby woods.
A3: Buxus sempervirens | B3: Low formal hedge, balls | C3: Optional | D3: Sheared 2-3x/yr to hold form. Boxwood blight has been found in Oregon nurseries and landscapes since 2011. Infected plants must be removed and destroyed. Leafminer and psyllid add spray cycles. | E3: Osmanthus delavayi | F3: Berberis aquifolium 'Compacta' (informal low mass); dwarf Arctostaphylos or prostrate rosemary on hot dry edges | G3: Osmanthus prefers drainage - Group 2 and 3 first. On Group 1, use Berberis aquifolium. | H3: 3 shearings/yr down to 1 | I3: The best payback of the hedge conversions, because shearing frequency drives the cost. Boxwood blight is the other risk: once it reaches a hedge, it can take the whole planting.
A4: Thuja occidentalis | B4: 'Emerald Green' privacy hedge | C4: Remove soon | D4: Shallow-rooted and increasingly drought-stressed in valley summers. Flagging, spider mites, Phytophthora, deer browse. Individual plants die and leave gaps that cannot be filled in kind. | E4: Calocedrus decurrens (incense cedar) | F4: Morella californica (shorter); Hesperocyparis arizonica on sharply drained sites only | G4: Incense cedar on Groups 2 and 3; wax myrtle on Group 1. Do NOT default to western redcedar - Thuja plicata is itself in drought decline across the valley. | H4: Shearing plus ongoing gap replacement, down to periodic thinning | I4: If plants are already dying one at a time, replacing the whole run once costs less than patching it every year.
A5: Photinia x fraseri | B5: Red tip hedge | C5: Remove soon | D5: Entomosporium leaf spot is near-inevitable in valley wet springs, and shearing makes it worse by forcing susceptible new growth. Fungicide cycles plus shearing means up to 4 visits/yr on a plant that keeps declining. | E5: Osmanthus x burkwoodii | F5: Morella californica; Arbutus unedo 'Compacta' (red stems, winter flowers and fruit) | G5: Osmanthus and Arbutus want drainage. Wax myrtle for Group 1. | H5: Up to 4 visits/yr down to 1, and spraying stops | I5: Leaf spot returns every wet spring. Replacing it ends a recurring failure rather than changing a healthy planting.
A6: Betula pendula / papyrifera | B6: Specimen or clump birch | C6: Remove soon | D6: Bronze birch borer plus chronic summer drought stress. Aphid honeydew on cars and patios. Once crown dieback starts in the valley it does not reverse. | E6: Parrotia persica | F6: Quercus imbricaria (if space); Arbutus unedo 'Marina' multi-stem (evergreen); Acer griseum (not in Palette; needs more water) | G6: Parrotia works Groups 1 and 2, caution on 3. Bur or swamp white oak for wet Group 1 with room. | H6: Removal risk falls; pruning roughly halves | I6: No drought-tolerant tree has the same white bark. Choose the replacement for bark, structure and fall color instead.
A7: Pyrus calleryana | B7: 'Bradford' street/yard tree | C7: Remove soon | D7: Included bark at codominant unions causes structural failure at roughly 15-25 years, usually in an ice or wind event. Fireblight. Invasive seedling spread from fertile cultivar crosses. | E7: Parrotia persica | F7: Maackia amurensis (under wires); Quercus imbricaria (larger sites); Arbutus unedo 'Marina' | G7: Parrotia and Maackia are fine on Groups 1 and 2. Shingle oak on Groups 1 and 2 where there is room. Arbutus needs drainage: Groups 2 and 3 only. Maackia for small rooting volume. | H7: Structural pruning cycle replaces failure response | I7: Replacement rarely pays for itself in maintenance savings. The reason is timing: the tree will fail, and a planned removal is cheaper and safer than an emergency one.
A8: Prunus cerasifera | B8: 'Thundercloud' flowering plum | C8: Remove soon | D8: Short-lived at 20-25 years. Aphids, brown rot, bacterial canker, borers. Fruit litter and root suckering. Most valley specimens are already past their useful life. | E8: Cotinus coggygria 'Royal Purple' | F8: Parrotia persica; Maackia amurensis; Cercis canadensis 'Forest Pansy' (not in Palette; needs more water) | G8: Cotinus wants drainage - Group 2 and 3. Parrotia for Group 1. | H8: Ends aphid/fruit callbacks; pruning drops sharply | I8: Smokebush keeps the purple foliage that made the plum the choice, and it handles drought. Matching the look is what makes the change stick.
A9: Fraxinus spp. | B9: Oregon, green and white ash | C9: Plan succession | D9: EAB is confirmed in five northern Willamette Valley counties, as close as Salem. It is not confirmed in Lane County as of August 2026. Untreated ash will die once EAB arrives. Treated ash needs injection every 2-3 years while EAB is present. Eugene does not allow ash planting on public land. | E9: Decide per tree in the Ash Register tab: treat, plant first, or replace. Replacements: Quercus bicolor (wet) / Quercus garryana (upland) | F9: Quercus macrocarpa; Malus fusca (wet sites, small spaces); Quercus imbricaria; Parrotia persica. Riparian sites: natives only (Malus fusca, Salix, Q. garryana). | G9: Swamp white oak is the strongest analog for the wet bottomland niche Oregon ash holds. Bur oak second. Garry oak on Group 3. Use Pacific crabapple between oaks to keep the oak share down. | H9: Treat: injection every 2-3 years. Replace: ends treatment and the risk of a dead tree. | I9: For one tree, treatment usually costs less than replacement over 15 years. Treat healthy, valuable trees before EAB arrives. For the rest, plant a successor now so there is shade when the ash comes out. Never let an untreated ash die near a house or road.
A11: READING THE CLASS COLUMN
A12: REMOVE SOON: the plant is failing, structurally unsound or under pest pressure. The cost will come anyway; the choice is when. Maintenance savings are not the reason. Hazard, timing and the cost of waiting are.
A13: OPTIONAL: the plant is healthy but costly to keep. The cost curve is the reason. It needs a long horizon: 10 or more years under the same management. Payback runs 5-10 years.
A14: Do Remove soon replacements first. Their results show how the palette performs before Optional work starts.
A16: HEDGEROW OPTION
A17: For laurel, arborvitae and photinia hedges on sites 8 ft wide or more, consider a mixed hedgerow. It replaces one species with 6-10 and ends shearing. See the Hedgerow Design tab.
A19: SOURCE NOTE
A20: Invasive status: City of Eugene Native and Non-Native Plant List (Ordinance 20351, Exhibit F) names English laurel, sweet cherry and black locust as invasive. English laurel is not confirmed on the state noxious weed list.
A22: PLAN SUCCESSION CLASS (ash in Lane County)
A23: PLAN SUCCESSION: the plant is healthy now but faces a known threat. Today this means ash before EAB reaches Lane County. It is not failing. Treat high-value trees and plant a successor for the rest. It becomes Remove soon when the threat arrives. See the Ash EAB tab.

Sheet Ash EAB
A1: ASH TREES AND EMERALD ASH BORER (EAB)
A2: Use this tab for every ash tree you manage. Decide per tree: treat, plant a successor first, or remove and replace. Record each tree in the Ash Register tab. The recommendation and costs fill in there.
A4: EAB STATUS — check every 3 months
A5: Confirmed counties | B5: Clackamas, Marion, Multnomah, Washington and Yamhill (ODA quarantine). Nearest confirmed sites to Eugene: Salem and Silverton (2026).
A6: Lane County | B6: Not confirmed as of August 2026 reports. Ash in Lane is in the Plan succession window: treatment works best now, before infestation.
A7: Status last checked | B7: 46301 | C7: Update this date each time you check. Sources: oregon-eab-geo.hub.arcgis.com and the ODA EAB page.
A8: Next check due | B8: =$B$7+90 -> 46391 | C8: Amber within 30 days, red when overdue.
A10: COSTS — placeholders, replace with local prices
A11: Injection cost ($ per inch DBH, per treatment) | B11: 12 | C11: Emamectin benzoate trunk injection. Published range about $7-16 per inch.
A12: Retreatment interval (years) | B12: 2 | C12: Labels allow 2-3 years. Use 2 to stay conservative.
A13: Planned removal ($ per inch DBH) | B13: 80 | C13: Placeholder. An 18 in tree = $1,440. Published range for 18 in: about $1,200-2,400.
A14: Emergency multiplier for dead ash | B14: 1.5 | C14: Dead ash is brittle. Lift or crane, more rigging, more risk.
A15: Replacement tree, installed, with 3-year establishment ($) | B15: 1350 | C15: Stock, install labor and 3-year establishment care. Matches Conversion Economics.
A16: DBH used in Conversion Economics (in) | B16: 18 | C16: Example tree for the Ash column on that tab.
A17: Planning horizon (years) | B17: ='Start Here'!$B$7 -> 15 | C17: From Start Here.
A19: REGISTER SUMMARY — updates from the Ash Register
A20: Ash trees recorded | B20: =COUNTA('Ash Register'!$D$3:$D$302) -> 0
A21: Recommendation: REMOVE NOW | B21: =COUNTIF('Ash Register'!$J$3:$J$302,"REMOVE NOW*") -> 0
A22: Recommendation: GRAY ZONE | B22: =COUNTIF('Ash Register'!$J$3:$J$302,"GRAY*") -> 0
A23: Recommendation: TREAT | B23: =COUNTIF('Ash Register'!$J$3:$J$302,"TREAT") -> 0
A24: Recommendation: PLANT FIRST, REMOVE LATER | B24: =COUNTIF('Ash Register'!$J$3:$J$302,"PLANT FIRST*") -> 0
A25: Recommendation: REMOVE AND REPLACE | B25: =COUNTIF('Ash Register'!$J$3:$J$302,"REMOVE AND*") -> 0
A26: Trees under treatment | B26: =COUNTIF('Ash Register'!$Q$3:$Q$302,"Treated") -> 0
A27: Treatments overdue | B27: =COUNTIFS('Ash Register'!$S$3:$S$302,"<"&TODAY()) -> 0
A28: Inches of DBH under treatment | B28: =SUMIF('Ash Register'!$Q$3:$Q$302,"Treated",'Ash Register'!$D$3:$D$302) -> 0
A29: Treatment cost per year, all treated trees | B29: =SUMIF('Ash Register'!$Q$3:$Q$302,"Treated",'Ash Register'!$D$3:$D$302)*'Ash EAB'!$B$11/'Ash EAB'!$B$12 -> 0
A31: DECISION RULES — the Ash Register applies these
A32: 1. | B32: More than 50% canopy dieback: REMOVE NOW. The damaged trunk cannot move insecticide. Dead ash turns brittle fast.
A33: 2. | B33: 30-50% dieback: GRAY ZONE. Assess the structure. Treat only a high-value tree with sound structure. Otherwise remove.
A34: 3. | B34: Less than 30% dieback and high value: TREAT. Inject every 2-3 years for as long as EAB is present. Start before EAB arrives.
A35: 4. | B35: Less than 30% dieback, EAB signs present, not high value: REMOVE AND REPLACE on a planned schedule.
A36: 5. | B36: Less than 30% dieback, no signs, not high value: PLANT FIRST, REMOVE LATER (phased replacement, below).
A37: 6. | B37: Near a target (house, road, play area): never let an untreated ash die in place.
A39: CONVERSION CLASS — PLAN SUCCESSION
A40: Ash in Lane County is in the Plan succession class, not Remove soon. The tree is healthy now, but it will decline once EAB arrives unless it is treated. It is not failing. Decide per tree: protect the trees worth protecting, and plant successors for the rest while the ash still gives shade. When EAB is confirmed in Lane County, untreated ash moves to Remove soon.
A42: THE COSTS
A43: For one tree, treatment is usually cheaper than replacement over 15 years. An 18 in ash costs about $216 per treatment, or about $1,700 over 15 years. Removal and replacement costs about $2,800. So replacement is not a saving. Treatment also keeps the canopy. Replacement makes sense when the tree is low value, declining or badly placed, or when no one will commit to long-term treatment.
A45: PHASED REPLACEMENT — plant first, remove later
A46: Step 1 | B46: Plant the successor now, in light: outside the ash dripline or in a canopy gap.
A47: Step 2 | B47: Water it on the Establishment Water schedule. Add it to the Install Log. Copy its Install ID to the Ash Register.
A48: Step 3 | B48: Check the ash at each visit: update dieback % and EAB signs in the register.
A49: Step 4 | B49: Remove the ash when dieback reaches 30%, when EAB is confirmed in Lane County, or when the successor gives useful shade (often year 5-8).
A50: Step 5 | B50: Plan the removal. Waiting until the ash dies adds the emergency multiplier.
A52: EAB SIGNS — field check
A53: • | B53: D-shaped exit holes, about 1/8 in wide, in the bark.
A54: • | B54: Woodpecker damage: patches of light, flaked bark ('blonding').
A55: • | B55: Vertical bark splits with S-shaped tunnels under the bark.
A56: • | B56: Sprouts on the trunk or at the base.
A57: • | B57: Crown thinning from the top down.
A58: A suspected EAB find in Lane County would be a new county record. Report it to the Oregon Invasive Species Hotline (oregoninvasiveshotline.org) before moving any wood from the site.
A60: QUARANTINE AND WOOD HANDLING
A61: 1. | B61: Current quarantine: Clackamas, Marion, Multnomah, Washington and Yamhill counties. Ash, olive and white fringetree material cannot leave these counties without an ODA compliance agreement. This includes logs, chips, mulch, stumps, roots, branches and nursery stock. Hardwood firewood cannot leave either.
A62: 2. | B62: Never bring ash material or hardwood firewood from those counties into Lane County. This includes loads from work sites in those counties.
A63: 3. | B63: If Lane County is added: ash chips and wood must stay in the county. Plan local disposal for every ash removal. Chip and leave on site where the owner allows.
A64: 4. | B64: Do not move any wood off a site with suspected EAB until it is reported.
A66: REMOVING DEAD OR DYING ASH
A67: 1. | B67: EAB-killed ash dries and turns brittle within 1-2 years of death. Limbs fail without warning.
A68: 2. | B68: Do not climb an ash with more than 50% dieback. Use a lift or crane. Include it in the cost.
A69: 3. | B69: Cost dead-tree removal at the emergency multiplier above.
A71: RIPARIAN AND WETLAND SITES
A72: Oregon ash often grows in wetlands and along streams. On these sites, replace with natives only. Swamp white oak is not native to Oregon. Use it in landscape settings, not in restoration or riparian work.
A73: Native options | B73: Pacific crabapple (Malus fusca); Hooker's willow and other native willows; Oregon white oak on drier edges; red-osier dogwood and Pacific ninebark below.
A74: Permits | B74: Work in wetlands and stream buffers may need city, county or state permits. Check before work starts.
A75: Future option | B75: State scientists are planting Oregon ash to find trees with natural EAB resistance. If resistant stock becomes available, revisit the Oregon ash row in the Palette.
A77: WHEN EAB IS CONFIRMED IN LANE COUNTY
A78: 1. | B78: Move every untreated ash from Plan succession to Remove soon.
A79: 2. | B79: Treat every TREAT tree that is not yet treated. Do it this season.
A80: 3. | B80: Re-check every tree in the register. Update dieback and signs.
A81: 4. | B81: Check whether Lane is added to the quarantine. Update disposal plans.
A82: 5. | B82: Update the status rows at the top of this tab.
A84: SOURCES
A85: ODA: Emerald Ash Borer | B85: oregon.gov/oda/ippm/survey-treatment/pages/emerald-ash-borer.aspx — quarantine counties and rules.
A86: Capital Press, 2026-06-24 | B86: EAB spreads to Tualatin, Newberg and Silverton.
A87: KPTV, 2026-08-06 | B87: EAB detected in Salem and Beaverton.
A88: A.M. Leonard: EAB treatment vs. removal | B88: Injection about $7-16 per inch DBH per 2-year cycle. Removal ranges by size. Treat under 30% canopy loss; remove over 50%.
A89: Frerichs Tree Service: EAB pricing | B89: Example: $12 per inch DBH, every other year.
A90: KLCC, 2025-09-14 | B90: State scientists planting Oregon ash to find natural resistance.

Sheet Palette
A1: Scientific Name | B1: Common Name | C1: Genus | D1: Family | E1: Cultivar / Clone | F1: Habit | G1: Mature H x W (ft) | H1: Max Ht (ft) | I1: Summer Drought | J1: Winter-Wet / Clay | K1: Tier | L1: Grp 1 Clay | M1: Grp 2 Silt Loam | N1: Grp 3 Upland | O1: Under Wires | P1: Water Class | Q1: Sourcing 1-5 | R1: Pest / Disease Risk | S1: Spec Notes | T1: Source | U1: Review By
A2: Maclura pomifera 'White Shield' | B2: Osage Orange | C2: Maclura | D2: Moraceae | E2: 'White Shield' - thornless, fruitless male clone. VERIFY CLONE. | F2: Canopy tree · Dec | G2: 35-50 x 35-45 | H2: 50 | I2: Very High | J2: High | K2: A | L2: Yes | M2: Yes | N2: Yes | O2: No | P2: Standard | Q2: 4 | R2: Very few | S2: Near-indestructible on clay, compaction and drought. Entire value depends on getting the true clone - seedling Maclura is thorny and drops softball fruit. Inspect at the nursery. Watch for: Suckers if roots are damaged. | T2: SelecTree 536
A3: Quercus bicolor | B3: Swamp White Oak | C3: Quercus | D3: Fagaceae | E3: Straight species | F3: Canopy tree · Dec | G3: 50-60 x 50-60 | H3: 60 | I3: High | J3: Very High | K3: A | L3: Yes | M3: Yes | N3: Caution | O3: No | P3: Standard | Q3: 2 | R3: No significant regional issues | S3: Added specifically as the Oregon ash replacement. Tolerates extended winter saturation better than anything else on this list while still handling summer drought - that combination is exactly the wet-bottomland niche ash occupies and almost nothing else fills. Watch for: Acorn litter. | T3: Regional addition
A4: Quercus garryana | B4: Oregon White Oak | C4: Quercus | D4: Fagaceae | E4: Local provenance | F4: Canopy tree · Dec | G4: 50-80 x 50-80 | H4: 80 | I4: High | J4: High | K4: A | L4: Yes | M4: Yes | N4: Yes | O4: No | P4: Standard | Q4: 3 | R4: Minor oak twig blight; jumping gall wasp cosmetic | S4: The valley benchmark: evolved for exactly the wet-winter/dry-summer regime. Highest habitat value on the list. Slow establishment - do not overwater after year 3. Watch for: Acorn and leaf litter. | T4: Regional addition
A5: Quercus imbricaria | B5: Shingle Oak | C5: Quercus | D5: Fagaceae | E5: Straight species | F5: Canopy tree · Dec (marcescent) | G5: 50-60 x 50-60 | H5: 60 | I5: High | J5: High | K5: A | L5: Yes | M5: Yes | N5: Caution | O5: No | P5: Standard | Q5: 2 | R5: Few serious issues | S5: Marcescence is the whole story: excellent tall winter screen, but not for anyone who wants a tidy look. Know this before planting. Watch for: Holds dead brown leaves through winter. | T5: SelecTree 536
A6: Quercus macrocarpa | B6: Bur Oak | C6: Quercus | D6: Fagaceae | E6: Straight species | F6: Canopy tree · Dec | G6: 60-80 x 60-80 | H6: 80 | I6: High | J6: High | K6: A | L6: Yes | M6: Yes | N6: Yes | O6: No | P6: Standard | Q6: 2 | R6: No significant regional issues | S6: Strongest large-canopy option for winter-saturated clay. Tolerates compaction, seasonal flooding and drought. Slow, so plant larger stock or expect patience. Watch for: Large acorns - avoid over walks/patios. | T6: SelecTree 536
A7: Calocedrus decurrens | B7: Incense Cedar | C7: Calocedrus | D7: Cupressaceae | E7: Straight species | F7: Conifer · Evg | G7: 40-70 x 15-25 | H7: 70 | I7: High | J7: Moderate | K7: A | L7: Caution | M7: Yes | N7: Yes | O7: No | P7: Standard | Q7: 2 | R7: Generally clean; avoid saturated soil | S7: Best native tall evergreen screen. Narrow footprint suits property lines. Better drainage tolerance than most conifers but still avoid Dayton/Bashaw bottoms. | T7: Regional addition
A8: Pinus ponderosa | B8: Ponderosa Pine | C8: Pinus | D8: Pinaceae | E8: SPECIFY Willamette Valley seed source | F8: Conifer · Evg | G8: 60-100 x 25-40 | H8: 100 | I8: High | J8: High | K8: A | L8: Yes | M8: Yes | N8: Yes | O8: No | P8: Standard | Q8: 2 | R8: Sequoia pitch moth (cosmetic); avoid summer pruning | S8: Provenance is not optional: the Willamette Valley race tolerates seasonally saturated clay that interior sources will not. Confirm seed source in writing on the PO. Watch for: Needle and cone litter. | T8: Regional addition
A9: Amelanchier alnifolia | B9: Western Serviceberry | C9: Amelanchier | D9: Rosaceae | E9: Straight species | F9: Large shrub / small tree · Dec | G9: 6-15 x 6-12 | H9: 15 | I9: High | J9: Moderate | K9: A | L9: Caution | M9: Yes | N9: Yes | O9: Yes | P9: Standard | Q9: 2 | R9: Rust (cedar-apple type) near junipers; fireblight | S9: Spring bloom, edible fruit, fall color. Not for true bottomland; use on Group 1 only on a berm. | T9: OSU EM 8721
A10: Arbutus unedo | B10: Strawberry Tree | C10: Arbutus | D10: Ericaceae | E10: 'Compacta' / 'Elfin King' hedging; 'Marina' as small tree | F10: Large shrub / small tree · Evg | G10: 8-25 x 8-25 | H10: 25 | I10: High | J10: Moderate | K10: A | L10: Caution | M10: Yes | N10: Yes | O10: Caution | P10: Standard | Q10: 1 | R10: Root rot in saturated soil; otherwise clean | S10: Best hedge option from the source list and a strong multi-season performer. Keep off valley-bottom clay or plant on a raised berm. Site away from patios and light-colored paving. Watch for: Fruit drop stains hardscape. | T10: SelecTree 536
A11: Cotinus coggygria | B11: Smokebush | C11: Cotinus | D11: Anacardiaceae | E11: 'Royal Purple', 'Grace' (larger) | F11: Large shrub / small tree · Dec | G11: 10-15 x 10-15 | H11: 15 | I11: Very High | J11: Moderate | K11: A | L11: Caution | M11: Yes | N11: Yes | O11: Yes | P11: Standard | Q11: 1 | R11: Verticillium wilt on poorly drained sites | S11: The purple-foliage replacement for a flowering plum. Genuinely drought-hardy, unlike the Prunus it replaces. Can be coppiced for larger leaf color or grown on as a small multi-stem tree. | T11: Great Plant Picks
A12: Maackia amurensis | B12: Amur Maackia | C12: Maackia | D12: Fabaceae | E12: Straight species | F12: Small tree · Dec | G12: 20-30 x 20-30 | H12: 30 | I12: High | J12: Moderate | K12: A | L12: Yes | M12: Yes | N12: Caution | O12: Yes | P12: Standard | Q12: 3 | R12: No significant issues | S12: Borderline A/B - avoid true bottomland positions. Nitrogen fixer, tolerates poor and compacted soil, coppery peeling bark. One of few genuine under-wire options here. | T12: SelecTree 536
A13: Malus fusca | B13: Pacific Crabapple | C13: Malus | D13: Rosaceae | E13: Straight species, local seed source | F13: Small tree · Dec | G13: 15-30 x 15-25 | H13: 30 | I13: Moderate | J13: Very High | K13: A | L13: Yes | M13: Yes | N13: Caution | O13: Yes | P13: Standard | Q13: 3 | R13: Apple scab and rust possible; usually minor | S13: Native wetland-edge tree. One of very few non-oak trees for Group 1 clay. Thorny spurs; small fruit feeds birds. Center-row tree in a wet-site hedgerow. | T13: OSU EM 8721
... A32: Pistacia chinensis | B32: Chinese Pistache | C32: Pistacia | D32: Anacardiaceae | E32: Male clones only ('Keith Davey') | F32: Canopy tree · Dec | G32: 30-50 x 30-40 | H32: 50 | I32: High | J32: Low | K32: B | L32: No | M32: Yes | N32: Yes | O32: No | P32: Standard | Q32: 2 | R32: Verticillium wilt on poorly drained sites | S32: Sharp drainage is mandatory. Also runs slower and colors less reliably here than in its California trials - expect less reliable fall color than in California. Watch for: Female trees fruit heavily. | T32: SelecTree 536
A33: Quercus kelloggii | B33: California Black Oak | C33: Quercus | D33: Fagaceae | E33: SW Oregon provenance preferred | F33: Canopy tree · Dec | G33: 50-80 x 40-70 | H33: 80 | I33: High | J33: Low | K33: B | L33: No | M33: Caution | N33: Yes | O33: No | P33: Drought-adapted | Q33: 4 | R33: Known Phytophthora ramorum host (SOD quarantine is Curry Co., not Lane) | S33: Credible assisted-migration candidate. Taprooted and transplant-sensitive: plant small container stock or direct seed, never large B&B. Upland sites only. Watch for: Acorn and leaf litter. Check the sudden oak death quarantine boundary each year. | T33: SelecTree 536 | U33: 46447
A34: Quercus wislizeni | B34: Interior Live Oak | C34: Quercus | D34: Fagaceae | E34: Straight species | F34: Canopy tree · Evg | G34: 30-60 x 30-60 | H34: 60 | I34: High | J34: Low | K34: B | L34: No | M34: Caution | N34: Yes | O34: No | P34: Drought-adapted | Q34: 5 | R34: Generally clean | S34: Upland/well-drained only. Sourcing is the binding constraint - Portland reports evergreen oaks are hard to obtain in usable caliper. Arrange stock with a grower 2-3 years ahead. Watch for: Year-round leaf drop. | T34: SelecTree 536
A35: Tilia tomentosa | B35: Silver Linden | C35: Tilia | D35: Malvaceae | E35: 'Sterling' | F35: Canopy tree · Dec | G35: 50-70 x 40-50 | H35: 70 | I35: High | J35: High | K35: B | L35: Caution | M35: Yes | N35: No | O35: No | P35: Standard | Q35: 2 | R35: PRIME Japanese beetle host. ODA eradication funded only through the 2027 crop year; Lane Co. clear as of 2025 detections. | S35: Climatically fine, strategically risky. It is a 50-year tree facing a pest whose control depends on state funding renewed every two years. Use it only if you accept that risk. Watch for: Honeydew (less than other Tilia). Review when state Japanese beetle funding is next decided. | T35: SelecTree 536 | U35: 46569
A36: Hesperocyparis arizonica | B36: Arizona Cypress | C36: Hesperocyparis | D36: Cupressaceae | E36: 'Blue Ice', 'Carolina Sapphire' | F36: Conifer · Evg | G36: 30-50 x 15-25 | H36: 50 | I36: Very High | J36: Low | K36: B | L36: No | M36: Caution | N36: Yes | O36: No | P36: Drought-adapted | Q36: 2 | R36: Seiridium and Botryosphaeria canker in cool wet springs; Phytophthora in wet soil | S36: Fastest screen on the list, and the one most likely to fail. Restrict to sharply drained, sunny, well-ventilated sites. Never plant as a solid single-species hedge row - canker will take the whole run. | T36: SelecTree 536
A37: Salix hookeriana | B37: Hooker's Willow | C37: Salix | D37: Salicaceae | E37: Straight species; plant from live stakes | F37: Large shrub / small tree · Dec | G37: 10-25 x 10-20 | H37: 25 | I37: Moderate | J37: Very High | K37: B | L37: Yes | M37: Caution | N37: No | O37: No | P37: Standard | Q37: 1 | R37: Willow borers, rust, canker | S37: Aggressive roots. Keep 50+ ft from sewer lines, drains and foundations. Rural swales and pond edges only. Cheap and fast from cuttings. | T37: OSU EM 8721
A38: Arctostaphylos densiflora | B38: Vine Hill Manzanita | C38: Arctostaphylos | D38: Ericaceae | E38: 'Howard McMinn' - the reliable clone here | F38: Shrub · Evg | G38: 5-7 x 6-8 | H38: 7 | I38: Very High | J38: Low | K38: B | L38: No | M38: Caution | N38: Yes | O38: Yes | P38: Drought-adapted | Q38: 3 | R38: Phytophthora and branch dieback in wet or irrigated soil | S38: Superb on Group 3 slopes, reliably fatal in Group 1 bottoms. Never install on drip irrigation past year 2. Berm and use coarse mineral mulch, not bark. | T38: Great Plant Picks
A39: Ceanothus thyrsiflorus | B39: Blueblossom | C39: Ceanothus | D39: Rhamnaceae | E39: 'Victoria' is the hardiest reliable clone | F39: Shrub / hedge · Evg | G39: 6-12 x 6-12 | H39: 12 | I39: Very High | J39: Low | K39: B | L39: No | M39: Caution | N39: Yes | O39: Yes | P39: Drought-adapted | Q39: 2 | R39: Root rot with summer water; hard-freeze damage in severe winters | S39: Plan on a 10-15 year lifespan and no summer water. Fast and spectacular, but not a permanent plant; do not use it where a long-lived hedge is needed. Watch for: Short-lived. | T39: Great Plant Picks
A40: Cistus x hybridus | B40: White Rockrose | C40: Cistus | D40: Cistaceae | E40: Also C. x purpureus | F40: Shrub · Evg | G40: 2-4 x 4-6 | H40: 4 | I40: Very High | J40: Very Low | K40: B | L40: No | M40: Caution | N40: Yes | O40: Yes | P40: Drought-adapted | Q40: 1 | R40: Root rot in winter-wet soil; does not respond to hard pruning | S40: Group 3 slopes and hell strips only. Cannot be renovated by cutting back into old wood - plan on replacing it at 10-12 years. Watch for: Short-lived; gets leggy. | T40: Great Plant Picks
A41: Salvia rosmarinus | B41: Rosemary | C41: Salvia | D41: Lamiaceae | E41: 'Tuscan Blue' upright; 'Huntington Carpet' prostrate | F41: Shrub / hedge · Evg | G41: 2-5 x 2-4 | H41: 5 | I41: Very High | J41: Very Low | K41: B | L41: No | M41: Caution | N41: Yes | O41: Yes | P41: Drought-adapted | Q41: 1 | R41: Root rot on heavy soil | S41: Only on sharply drained sites. Popular, but on Group 1 clay use wax myrtle instead. Watch for: Gets woody and open with age. | T41: Great Plant Picks
A42: Aesculus x carnea | B42: Red Horsechestnut | C42: Aesculus | D42: Sapindaceae | E42: 'Briotii', 'Fort McNair' | F42: Canopy tree · Dec | G42: 30-40 x 30-40 | H42: 40 | I42: Low | J42: Moderate | K42: C | L42: Caution | M42: Caution | N42: No | O42: No | P42: Standard | Q42: 2 | R42: Guignardia leaf blotch; heat and drought scorch | S42: Fails the low-input standard. Scorches by August in the valley without extra water. Not recommended. Watch for: Fruit litter. | T42: SelecTree 536
A43: Thuja plicata | B43: Western Redcedar | C43: Thuja | D43: Cupressaceae | E43: — | F43: Conifer · Evg | G43: 50-70 x 15-25 | H43: 70 | I43: Low | J43: High | K43: C | L43: Caution | M43: Caution | N43: No | O43: No | P43: Standard | Q43: 1 | R43: Drought dieback now common in the valley | S43: Listed in EM 8721. Declining in valley summers. Only on shaded, moist Group 2 sites with long-term water. Not a low-input plant. | T43: OSU EM 8721
A44: Viburnum opulus | B44: Highbush Cranberry | C44: Viburnum | D44: Viburnaceae | E44: Native var. americanum ONLY | F44: Shrub · Dec | G44: 8-12 x 8-12 | H44: 12 | I44: Moderate | J44: High | K44: C | L44: Caution | M44: Caution | N44: No | O44: Yes | P44: Standard | Q44: 3 | R44: Viburnum leaf beetle; European form spreads by birds | S44: Listed in EM 8721. Nurseries often sell the European form, which spreads. Buy only the native variety, or do not use it. | T44: OSU EM 8721
A45: Fraxinus latifolia | B45: Oregon Ash | C45: Fraxinus | D45: Oleaceae | E45: — | F45: Canopy tree · Dec | G45: 40-80 x 30-50 | H45: 80 | I45: Moderate | J45: Very High | K45: Reject | L45: No | M45: No | N45: No | O45: No | P45: Standard | Q45: 1 | R45: Emerald ash borer confirmed in Oregon | S45: Listed in EM 8721 as wet-tolerant. It is the tree being replaced. Use Quercus bicolor or Malus fusca (natives only on riparian sites). For existing ash, see the Ash and EAB page. Review each year against EAB spread, and if EAB-resistant Oregon ash stock becomes available. | T45: OSU EM 8721 | U45: 46447
A46: Prunus avium | B46: Sweet Cherry | C46: Prunus | D46: Rosaceae | E46: — | F46: Canopy tree · Dec | G46: 30-40 x 25-35 | H46: 40 | I46: Moderate | J46: Moderate | K46: Reject | L46: No | M46: No | N46: No | O46: No | P46: Standard | Q46: 1 | R46: Bird-dispersed; spreads into woodland | S46: Listed in EM 8721, but it is a common invader of Willamette Valley oak woodland. Do not plant. | T46: OSU EM 8721
A47: Robinia pseudoacacia | B47: Black Locust | C47: Robinia | D47: Fabaceae | E47: — | F47: Canopy tree · Dec | G47: 40-60 x 30-40 | H47: 60 | I47: Very High | J47: High | K47: Reject | L47: No | M47: No | N47: No | O47: No | P47: Standard | Q47: 1 | R47: Locust borer; aggressive root suckers | S47: Listed in EM 8721. Suckers widely and naturalizes along valley roads and streams. Thorny. Do not plant. | T47: OSU EM 8721
A48: x Chitalpa tashkentensis | B48: Chitalpa | C48: Chitalpa | D48: Bignoniaceae | E48: 'Pink Dawn', 'Morning Cloud' | F48: Small tree · Dec | G48: 20-30 x 20-30 | H48: 30 | I48: High | J48: Very Low | K48: Reject | L48: No | M48: No | N48: Caution | O48: Yes | P48: Standard | Q48: 2 | R48: Powdery mildew; Xylella-associated decline | S48: A desert hybrid requiring heat and low humidity. Wrong climate, wrong soil, wrong lifespan for a long-term planting. Do not plant. Watch for: Weak wood; short-lived (15-25 yrs). | T48: SelecTree 536
A49: Elaeagnus umbellata | B49: Autumn Olive | C49: Elaeagnus | D49: Elaeagnaceae | E49: — | F49: Large shrub · Dec | G49: 12-20 x 12-20 | H49: 20 | I49: Very High | J49: Moderate | K49: Reject | L49: No | M49: No | N49: No | O49: No | P49: Standard | Q49: 1 | R49: Bird-dispersed; invasive in much of the US | S49: Listed in EM 8721 as an edible hedgerow plant. Widely invasive. Do not plant. | T49: OSU EM 8721

Sheet Hedgerow Design
A1: HEDGEROW DESIGN — MIXED PLANTINGS
A2: Based on OSU Extension EM 8721, A Guide to Hedgerows (Monnette and Hobbs; revised 2020, reviewed 2023). A hedgerow is a mixed, layered planting in place of a single-species hedge. It gives screening, habitat and pest resilience in one planting. Use it where the site has room.
A4: QUANTITY CALCULATOR
A5: Hedgerow length (ft) | B5: 100 | C5: Measure along the line.
A6: Number of rows | B6: 2 | C6: 2 for residential lines; 3 or more where width allows.
A7: Spacing in the row (ft) | B7: 6 | C7: EM 8721: 6-8 ft. Use 4-6 ft for a faster screen.
A8: Spacing between rows (ft) | B8: 8 | C8: EM 8721: 8-10 ft.
A9: Plants per row | B9: =ROUNDUP($B$5/$B$7,0)+1 -> 18 | C9: Staggered rows use the same count.
A10: Total plants | B10: =B9*$B$6 -> 36
A11: Approximate width needed (ft) | B11: =($B$6-1)*$B$8+$B$7 -> 14 | C11: Row spacing plus half a plant spread each side.
A12: Most rose-family plants allowed (30%) | B12: =ROUNDDOWN(B10*0.3,0) -> 10 | C12: Malus, Physocarpus, Oemleria, Rosa, Spiraea, Amelanchier, Holodiscus.
A13: Most Tier B plants allowed | B13: =ROUNDDOWN(B10*'Start Here'!$B$9,0) -> 3 | C13: From the Tier B cap in Start Here settings.
A14: Evergreens for winter screen (1 in 3 of one row) | B14: =ROUNDUP(B9/3,0) -> 6 | C14: Usually Morella californica in the screen row.
A16: DESIGN STANDARD — EM 8721 AND LOCAL ADAPTATION
A17: Parameter | B17: EM 8721 guidance | C17: Local adaptation
A18: Rows | B18: 4 or more rows is best. One row still gives some benefit. | C18: Residential lines: 2 staggered rows is the practical minimum. Use 3 or more on rural-fringe, commercial and HOA common areas.
A19: Width | B19: Wider than 20 ft works best for wildlife. A 20 ft hedgerow can hold 2 shrub rows around 1 tree row. | C19: Most residential lines give 6-12 ft. Do not expect much habitat value below about 10 ft. Use the full width where the land exists.
A20: Spacing | B20: 6-8 ft apart in the row. Rows 8-10 ft apart. | C20: Stagger the rows. Tighten to 4-6 ft in the row for a faster screen; this adds stock cost.
A21: Layering | B21: Tallest plants in the center row. Shorter plants between and along the edges. | C21: On a property line, put the tallest row on the side of the view to block. Keep the low row toward the area people use.
A22: Wind | B22: Plant rows across the prevailing wind. 40-50% density can cut wind speed by up to 75%. Winter windbreak: 2 evergreen rows plus 1 deciduous row. | C22: Valley storm winds come mostly from the south and southwest in winter. Summer winds come mostly from the north. Orient windbreaks to the season that matters on the site.
A23: Mulch and weeds | B23: At least 3 in of mulch. Keep a 6-8 ft mowed strip around the planting. | C23: 3-4 in of arborist chip. This agrees with the guide.
A24: Fire | B24: The mowed strip also serves as fire protection. | C24: Keep hedgerows out of the 0-5 ft zone around structures. Do not put resinous evergreens next to buildings. Apply defensible-space standards on wildland-edge sites.
A25: Animals | B25: Hardware cloth for beaver and nutria. Trunk guards for voles and mice. | C25: Use the Field Card deer rating. Install guards at planting, not as a later fix.
A26: Planting time | B26: Fall planting in mild climates. Roots grow through the winter rains. | C26: Agrees with the October-March planting window. Fall is preferred.
A27: Irrigation | B27: Year 1: weekly. Year 2: every 2 weeks. Year 3: monthly. Water deeply. Most hedgerows fail without water in the first years. | C27: Agrees with the Group 2 intervals (7 / 14 / 28 days). Establishment Water adds the Group 1 and Group 3 changes.
A28: Timeline | B28: 4-8 years to establish. 30+ years to reach maturity. | C28: Watering ends after year 3, but a hedgerow does not close until year 4-8. Keep up weed and edge control through the training tier (years 3-10).
A29: Diversity | B29: Plant a mix of species so one pest or disease cannot take the whole planting. | C29: Same rule as Program Review. One hedgerow can hold 6-10 species.
A31: TEMPLATE A — GROUP 1 WET CLAY, 3 ROWS, ABOUT 20 FT WIDE
A32: Row | B32: Species (pick 2-4 per row) | C32: Notes
A33: Center — tall | B33: Malus fusca; Quercus garryana or Q. bicolor (1 per 25-30 ft only); Salix hookeriana (rural sites only) | C33: Do not fill the center row with oak. Use crabapple between oaks.
A34: Middle — screen | B34: Morella californica; Physocarpus capitatus; Sambucus cerulea; Cornus sericea; Oemleria cerasiformis | C34: Put Morella in every 2nd or 3rd slot. It is the only evergreen in this template. Without it the row is open in winter.
A35: Edge — low | B35: Spiraea douglasii; Rosa nutkana; Symphoricarpos albus; Lonicera involucrata | C35: All spread by roots or layering. Give them a defined strip and a mowed edge.
A36: FAMILY LIMIT: Malus, Physocarpus, Oemleria, Rosa and Spiraea are all rose family (Rosaceae). Keep them to 3 of every 10 plants or fewer. Fill the rest with Morella, Cornus, Sambucus, Lonicera, Symphoricarpos and oak. A test mix built mostly from rose-family natives reached about 70% one family.
A38: TEMPLATE B — NARROW RESIDENTIAL, 2 STAGGERED ROWS, 8-10 FT WIDE
A39: Row | B39: Species | C39: Notes
A40: Back row | B40: Alternate Morella californica with Physocarpus capitatus (Groups 1-2) or Osmanthus x burkwoodii (Groups 2-3) | C40: Evergreen share gives winter screening. This is the direct replacement for a laurel or arborvitae hedge.
A41: Front row | B41: Ribes sanguineum; Cornus sericea 'Isanti'; Berberis aquifolium; Rosa nutkana only away from paths | C41: Mix for flowers, fruit and winter stem color. Informal. Not for a sheared look.
A43: WHERE IT FITS
A44: 1. | B44: Consider a hedgerow for laurel, arborvitae and photinia replacements. The site needs 8 ft of width or more.
A45: 2. | B45: Best fits rural-fringe, commercial, HOA common areas and larger lots. These have the width and the longer horizon.
A46: 3. | B46: Use it where an informal look is acceptable. Not where a sheared line is wanted.
A47: 4. | B47: Maintenance changes from shearing to renewal pruning and edge control. Use the Standard tier.
A48: 5. | B48: Farms may qualify for cost-share: NRCS runs EQIP; the Farm Service Agency runs CREP. Ask the local Soil and Water Conservation District. Residential properties usually do not qualify.
A50: LIMITS OF THE SOURCE
A51: EM 8721 is a Pacific Northwest list written mostly for farms. Its asterisk marks wet-soil tolerance only. It does not rate summer drought, urban soils or invasive risk. Its species were screened on both axes here. Six listed plants are in the Palette as C or Reject, with reasons: sweet cherry, autumn olive, black locust, Oregon ash, western redcedar and highbush cranberry (European form).

Sheet Establishment Water
A1: ESTABLISHMENT WATERING — YEARS 1-3
A2: Survival is decided in the first three dry seasons, not at planting. 'Drought-adapted' never means 'no water while establishing'. Write this plan down: whoever waters gets a printed copy (Watering Plan tab), and any replacement guarantee should refer to it.
A4: THE SEASON
A5: The watering season runs about June 15 to October 15 (length set in Start Here). Outside that window, extra water is not needed in a normal year. On Group 1 clay it does harm. Do not leave systems running into November.
A7: INTERVAL — DAYS BETWEEN WATERINGS (standard plants)
B8: Group 1 clay | C8: Group 2 silt loam | D8: Group 3 upland
A9: Year 1 | B9: 10 | C9: 7 | D9: 5
A10: Year 2 | B10: 21 | C10: 14 | D10: 10
A11: Year 3 | B11: 30 | C11: 28 | D11: 21
A12: Clay holds water, so intervals stretch; the risk there is root rot, not drought. Group 3 soils are shallow and dry out fast, so intervals shorten. Always water deep and slow. The goal is to pull roots down and out of the planting hole.
A14: VOLUME AND METHOD
A15: Trees | B15: 10 gallons per inch of trunk caliper each time. A 2 in tree takes 20 gallons.
A16: Shrubs | B16: About 1 gallon per gallon of container size. A 5 gal shrub takes about 5 gallons.
A17: Delivery | B17: Slow release only: gator bag, drip ring, or a hose on a trickle. Sprinklers and short spray cycles wet the mulch and nothing else. Build a 3 in soil ring at the root ball edge on flat sites.
A18: Mulch | B18: 3-4 in coarse arborist chip, pulled clear of the trunk flare, out to the dripline. Renew in years 2 and 3. Mulch does more for survival than extra watering.
A20: DROUGHT-ADAPTED OVERRIDE — READ THIS ONE
A21: The Palette 'Water Class' column marks drought-adapted species (manzanita, ceanothus, rockrose, rosemary, Arizona cypress, silktassel and the California oaks). They run 1.5x the interval in years 1-2 and get NO extra water from year 3 on. Summer water past year 2 kills these plants more often than drought does. Never put them on a drip zone. Never add them to an existing irrigation schedule. If no one will commit to shutting the water off, choose a Standard species.
A23: HEAT EVENT OVERRIDE
A24: Three or more days in a row above 100 F: water every planting once, whatever the schedule or year. This includes stock in years 4-5. Water in the early morning or evening. The 2021 heat dome killed established plants that were fine the week before. Track these as separate watering events.
A26: CALCULATOR — ONE SITE
A27: Enter one site. Pick each plant from the dropdown; its water class fills in from the Palette. Visits are counted once per site, so mixed plantings are not double-counted. Drought-adapted plants get water on a longer cycle during the same visits.
A28: Soil group (1 / 2 / 3) | B28: 2 | C28: From the Field Card.
A29: Labor hours per watering visit | B29: 1.5 | C29: Whole site, travel included. Placeholder.
A30: Dry season length (days) | B30: ='Start Here'!$B$8 -> 122 | C30: From Start Here settings.
A31: Labor rate ($/hour) | B31: ='Start Here'!$B$6 -> 150 | C31: From Start Here settings.
A33: Plant (from Palette) | B33: Water class | C33: Caliper (in) | D33: Container (gal) | E33: Count | F33: Gal each, per watering | G33: Yr 1 waterings | H33: Yr 2 waterings | I33: Yr 3 waterings | J33: 3-yr gallons
A34: Morella californica | B34: =IF($A34="","",IFERROR(INDEX(Palette!$P$2:$P$151,MATCH($A34,Palette!$A$2:$A$151,0)),"Standard")) -> Standard | C34: 0 | D34: 5 | E34: 25 | F34: =IF(N($E34)=0,0,IF(N($C34)>0,$C34*10,N($D34))) -> 5 | G34: =IF(N($E34)=0,0,ROUNDUP($B$30/IF($B34="Drought-adapted",ROUND(INDEX($B$9:$D$11,1,$B$28)*1.5,0),INDEX($B$9:$D$11,1,$B$28)),0)) -> 18 | H34: =IF(N($E34)=0,0,ROUNDUP($B$30/IF($B34="Drought-adapted",ROUND(INDEX($B$9:$D$11,2,$B$28)*1.5,0),INDEX($B$9:$D$11,2,$B$28)),0)) -> 9 | I34: =IF(OR(N($E34)=0,$B34="Drought-adapted"),0,ROUNDUP($B$30/INDEX($B$9:$D$11,3,$B$28),0)) -> 5 | J34: =F34*N(E34)*(G34+H34+I34) -> 4000
B35: =IF($A35="","",IFERROR(INDEX(Palette!$P$2:$P$151,MATCH($A35,Palette!$A$2:$A$151,0)),"Standard")) | F35: =IF(N($E35)=0,0,IF(N($C35)>0,$C35*10,N($D35))) -> 0 | G35: =IF(N($E35)=0,0,ROUNDUP($B$30/IF($B35="Drought-adapted",ROUND(INDEX($B$9:$D$11,1,$B$28)*1.5,0),INDEX($B$9:$D$11,1,$B$28)),0)) -> 0 | H35: =IF(N($E35)=0,0,ROUNDUP($B$30/IF($B35="Drought-adapted",ROUND(INDEX($B$9:$D$11,2,$B$28)*1.5,0),INDEX($B$9:$D$11,2,$B$28)),0)) -> 0 | I35: =IF(OR(N($E35)=0,$B35="Drought-adapted"),0,ROUNDUP($B$30/INDEX($B$9:$D$11,3,$B$28),0)) -> 0 | J35: =F35*N(E35)*(G35+H35+I35) -> 0
B36: =IF($A36="","",IFERROR(INDEX(Palette!$P$2:$P$151,MATCH($A36,Palette!$A$2:$A$151,0)),"Standard")) | F36: =IF(N($E36)=0,0,IF(N($C36)>0,$C36*10,N($D36))) -> 0 | G36: =IF(N($E36)=0,0,ROUNDUP($B$30/IF($B36="Drought-adapted",ROUND(INDEX($B$9:$D$11,1,$B$28)*1.5,0),INDEX($B$9:$D$11,1,$B$28)),0)) -> 0 | H36: =IF(N($E36)=0,0,ROUNDUP($B$30/IF($B36="Drought-adapted",ROUND(INDEX($B$9:$D$11,2,$B$28)*1.5,0),INDEX($B$9:$D$11,2,$B$28)),0)) -> 0 | I36: =IF(OR(N($E36)=0,$B36="Drought-adapted"),0,ROUNDUP($B$30/INDEX($B$9:$D$11,3,$B$28),0)) -> 0 | J36: =F36*N(E36)*(G36+H36+I36) -> 0
B37: =IF($A37="","",IFERROR(INDEX(Palette!$P$2:$P$151,MATCH($A37,Palette!$A$2:$A$151,0)),"Standard")) | F37: =IF(N($E37)=0,0,IF(N($C37)>0,$C37*10,N($D37))) -> 0 | G37: =IF(N($E37)=0,0,ROUNDUP($B$30/IF($B37="Drought-adapted",ROUND(INDEX($B$9:$D$11,1,$B$28)*1.5,0),INDEX($B$9:$D$11,1,$B$28)),0)) -> 0 | H37: =IF(N($E37)=0,0,ROUNDUP($B$30/IF($B37="Drought-adapted",ROUND(INDEX($B$9:$D$11,2,$B$28)*1.5,0),INDEX($B$9:$D$11,2,$B$28)),0)) -> 0 | I37: =IF(OR(N($E37)=0,$B37="Drought-adapted"),0,ROUNDUP($B$30/INDEX($B$9:$D$11,3,$B$28),0)) -> 0 | J37: =F37*N(E37)*(G37+H37+I37) -> 0
B38: =IF($A38="","",IFERROR(INDEX(Palette!$P$2:$P$151,MATCH($A38,Palette!$A$2:$A$151,0)),"Standard")) | F38: =IF(N($E38)=0,0,IF(N($C38)>0,$C38*10,N($D38))) -> 0 | G38: =IF(N($E38)=0,0,ROUNDUP($B$30/IF($B38="Drought-adapted",ROUND(INDEX($B$9:$D$11,1,$B$28)*1.5,0),INDEX($B$9:$D$11,1,$B$28)),0)) -> 0 | H38: =IF(N($E38)=0,0,ROUNDUP($B$30/IF($B38="Drought-adapted",ROUND(INDEX($B$9:$D$11,2,$B$28)*1.5,0),INDEX($B$9:$D$11,2,$B$28)),0)) -> 0 | I38: =IF(OR(N($E38)=0,$B38="Drought-adapted"),0,ROUNDUP($B$30/INDEX($B$9:$D$11,3,$B$28),0)) -> 0 | J38: =F38*N(E38)*(G38+H38+I38) -> 0
B39: =IF($A39="","",IFERROR(INDEX(Palette!$P$2:$P$151,MATCH($A39,Palette!$A$2:$A$151,0)),"Standard")) | F39: =IF(N($E39)=0,0,IF(N($C39)>0,$C39*10,N($D39))) -> 0 | G39: =IF(N($E39)=0,0,ROUNDUP($B$30/IF($B39="Drought-adapted",ROUND(INDEX($B$9:$D$11,1,$B$28)*1.5,0),INDEX($B$9:$D$11,1,$B$28)),0)) -> 0 | H39: =IF(N($E39)=0,0,ROUNDUP($B$30/IF($B39="Drought-adapted",ROUND(INDEX($B$9:$D$11,2,$B$28)*1.5,0),INDEX($B$9:$D$11,2,$B$28)),0)) -> 0 | I39: =IF(OR(N($E39)=0,$B39="Drought-adapted"),0,ROUNDUP($B$30/INDEX($B$9:$D$11,3,$B$28),0)) -> 0 | J39: =F39*N(E39)*(G39+H39+I39) -> 0
A41: Site watering visits | G41: =MAX(G34:G39) -> 18 | H41: =MAX(H34:H39) -> 9 | I41: =MAX(I34:I39) -> 5 | J41: =SUM(G41:I41) -> 32
A42: Gallons applied | G42: =SUMPRODUCT($F$34:$F$39,$E$34:$E$39,G34:G39) -> 2250 | H42: =SUMPRODUCT($F$34:$F$39,$E$34:$E$39,H34:H39) -> 1125 | I42: =SUMPRODUCT($F$34:$F$39,$E$34:$E$39,I34:I39) -> 625 | J42: =SUM(G42:I42) -> 4000
A43: Labor hours | G43: =G41*$B$29 -> 27 | H43: =H41*$B$29 -> 13.5 | I43: =I41*$B$29 -> 7.5 | J43: =SUM(G43:I43) -> 48
A44: Watering cost if hired out | G44: =G43*$B$31 -> 4050 | H44: =H43*$B$31 -> 2025 | I44: =I43*$B$31 -> 1125 | J44: =SUM(G44:I44) -> 7200
A45: The bold 3-year total (right) feeds the 'Hired watering' line in Conversion Economics. Reliable watering is the biggest survival factor you control.
A47: WHAT TO HAND OVER
A48: At install | B48: The Watering Plan tab, printed: dates, gallons per plant, method and the shut-off date. Not verbal instructions.
A49: On the schedule | B49: Each watering visit as a scheduled item, if a contractor waters.
A50: In writing | B50: Any replacement guarantee depends on the plan being followed. Name who waters: owner or contractor.
A51: Year 3 exit | B51: Say when watering stops and why. Watering an oak into year 6 makes a shallow-rooted tree that fails in the first real drought.
A53: CHECKS AND LIMITS
A54: Independent check: OSU EM 8721 gives the same schedule for new hedgerows (weekly, then every 2 weeks, then monthly). That matches the Group 2 column here. The Group 1 and Group 3 columns are local changes to that base.
A55: Volumes and intervals are standard arboricultural practice adapted to local soils, not site measurements. Check soil moisture at 6-8 in with a probe on the first plantings and adjust the yellow interval table.

Sheet Watering Plan
A1: YOUR NEW PLANTING — WATERING PLAN
A2: Please keep this page. Any replacement guarantee depends on following it.
A3: Owner
A4: Site address
A5: Install date
A6: Watering done by
A7: Contact
A8: Soil group | B8: ='Establishment Water'!$B$28 -> 2
A9: Stop all watering after | B9: =IF($B$5="","(enter install date)",DATE(IF($B$5="","",YEAR($B$5)+IF(MONTH($B$5)>=10,1,0))+2,10,15)) -> (enter install date)
A11: SCHEDULE — water every ... days, June 15 to October 15
A12: Plant | B12: Gallons each plant, each time | C12: =IF($B$5="","Summer "&1,"Summer "&(IF($B$5="","",YEAR($B$5)+IF(MONTH($B$5)>=10,1,0))+0)) -> Summer 1 | D12: =IF($B$5="","Summer "&2,"Summer "&(IF($B$5="","",YEAR($B$5)+IF(MONTH($B$5)>=10,1,0))+1)) -> Summer 2 | E12: =IF($B$5="","Summer "&3,"Summer "&(IF($B$5="","",YEAR($B$5)+IF(MONTH($B$5)>=10,1,0))+2)) -> Summer 3
A13: =IF('Establishment Water'!$A34="","",'Establishment Water'!$A34) -> Morella californica | B13: =IF($A13="","",'Establishment Water'!$F34) -> 5 | C13: =IF($A13="","",IF('Establishment Water'!$B34="Drought-adapted",ROUND(INDEX('Establishment Water'!$B$9:$D$11,1,'Establishment Water'!$B$28)*1.5,0),INDEX('Establishment Water'!$B$9:$D$11,1,'Establishment Water'!$B$28))&" days") -> 7 days | D13: =IF($A13="","",IF('Establishment Water'!$B34="Drought-adapted",ROUND(INDEX('Establishment Water'!$B$9:$D$11,2,'Establishment Water'!$B$28)*1.5,0),INDEX('Establishment Water'!$B$9:$D$11,2,'Establishment Water'!$B$28))&" days") -> 14 days | E13: =IF($A13="","",IF('Establishment Water'!$B34="Drought-adapted","No water",INDEX('Establishment Water'!$B$9:$D$11,3,'Establishment Water'!$B$28)&" days")) -> 28 days
A14: =IF('Establishment Water'!$A35="","",'Establishment Water'!$A35) | B14: =IF($A14="","",'Establishment Water'!$F35) | C14: =IF($A14="","",IF('Establishment Water'!$B35="Drought-adapted",ROUND(INDEX('Establishment Water'!$B$9:$D$11,1,'Establishment Water'!$B$28)*1.5,0),INDEX('Establishment Water'!$B$9:$D$11,1,'Establishment Water'!$B$28))&" days") | D14: =IF($A14="","",IF('Establishment Water'!$B35="Drought-adapted",ROUND(INDEX('Establishment Water'!$B$9:$D$11,2,'Establishment Water'!$B$28)*1.5,0),INDEX('Establishment Water'!$B$9:$D$11,2,'Establishment Water'!$B$28))&" days") | E14: =IF($A14="","",IF('Establishment Water'!$B35="Drought-adapted","No water",INDEX('Establishment Water'!$B$9:$D$11,3,'Establishment Water'!$B$28)&" days"))
A15: =IF('Establishment Water'!$A36="","",'Establishment Water'!$A36) | B15: =IF($A15="","",'Establishment Water'!$F36) | C15: =IF($A15="","",IF('Establishment Water'!$B36="Drought-adapted",ROUND(INDEX('Establishment Water'!$B$9:$D$11,1,'Establishment Water'!$B$28)*1.5,0),INDEX('Establishment Water'!$B$9:$D$11,1,'Establishment Water'!$B$28))&" days") | D15: =IF($A15="","",IF('Establishment Water'!$B36="Drought-adapted",ROUND(INDEX('Establishment Water'!$B$9:$D$11,2,'Establishment Water'!$B$28)*1.5,0),INDEX('Establishment Water'!$B$9:$D$11,2,'Establishment Water'!$B$28))&" days") | E15: =IF($A15="","",IF('Establishment Water'!$B36="Drought-adapted","No water",INDEX('Establishment Water'!$B$9:$D$11,3,'Establishment Water'!$B$28)&" days"))
A16: =IF('Establishment Water'!$A37="","",'Establishment Water'!$A37) | B16: =IF($A16="","",'Establishment Water'!$F37) | C16: =IF($A16="","",IF('Establishment Water'!$B37="Drought-adapted",ROUND(INDEX('Establishment Water'!$B$9:$D$11,1,'Establishment Water'!$B$28)*1.5,0),INDEX('Establishment Water'!$B$9:$D$11,1,'Establishment Water'!$B$28))&" days") | D16: =IF($A16="","",IF('Establishment Water'!$B37="Drought-adapted",ROUND(INDEX('Establishment Water'!$B$9:$D$11,2,'Establishment Water'!$B$28)*1.5,0),INDEX('Establishment Water'!$B$9:$D$11,2,'Establishment Water'!$B$28))&" days") | E16: =IF($A16="","",IF('Establishment Water'!$B37="Drought-adapted","No water",INDEX('Establishment Water'!$B$9:$D$11,3,'Establishment Water'!$B$28)&" days"))
A17: =IF('Establishment Water'!$A38="","",'Establishment Water'!$A38) | B17: =IF($A17="","",'Establishment Water'!$F38) | C17: =IF($A17="","",IF('Establishment Water'!$B38="Drought-adapted",ROUND(INDEX('Establishment Water'!$B$9:$D$11,1,'Establishment Water'!$B$28)*1.5,0),INDEX('Establishment Water'!$B$9:$D$11,1,'Establishment Water'!$B$28))&" days") | D17: =IF($A17="","",IF('Establishment Water'!$B38="Drought-adapted",ROUND(INDEX('Establishment Water'!$B$9:$D$11,2,'Establishment Water'!$B$28)*1.5,0),INDEX('Establishment Water'!$B$9:$D$11,2,'Establishment Water'!$B$28))&" days") | E17: =IF($A17="","",IF('Establishment Water'!$B38="Drought-adapted","No water",INDEX('Establishment Water'!$B$9:$D$11,3,'Establishment Water'!$B$28)&" days"))
A18: =IF('Establishment Water'!$A39="","",'Establishment Water'!$A39) | B18: =IF($A18="","",'Establishment Water'!$F39) | C18: =IF($A18="","",IF('Establishment Water'!$B39="Drought-adapted",ROUND(INDEX('Establishment Water'!$B$9:$D$11,1,'Establishment Water'!$B$28)*1.5,0),INDEX('Establishment Water'!$B$9:$D$11,1,'Establishment Water'!$B$28))&" days") | D18: =IF($A18="","",IF('Establishment Water'!$B39="Drought-adapted",ROUND(INDEX('Establishment Water'!$B$9:$D$11,2,'Establishment Water'!$B$28)*1.5,0),INDEX('Establishment Water'!$B$9:$D$11,2,'Establishment Water'!$B$28))&" days") | E18: =IF($A18="","",IF('Establishment Water'!$B39="Drought-adapted","No water",INDEX('Establishment Water'!$B$9:$D$11,3,'Establishment Water'!$B$28)&" days"))
A20: HOW TO WATER
A21: 1. | B21: Water slowly at the base of each plant: drip ring, soaker, watering bag, or a hose on a trickle. Do not use a sprinkler.
A22: 2. | B22: Water deeply and less often. Short, frequent watering keeps roots shallow.
A23: 3. | B23: Keep the mulch 3-4 in deep. Keep it pulled back from the trunk.
A24: 4. | B24: Heat wave (3 or more days above 100 F): give every plant one extra watering, early morning or evening, in any year.
A25: 5. | B25: 'No water' means no water. Those plants are harmed by summer water after the second year.
A26: 6. | B26: Stop all watering after the date above. Dry summers after year 3 make deep, strong roots.
A27: 7. | B27: Call your contact if leaves wilt, brown or drop outside of fall.

Sheet Conversion Economics
A1: CONVERSION ECONOMICS
A2: Blue cells are placeholder estimates. Replace them with local figures before relying on the results. The shape of the result holds; the paybacks will move.
A4: Labor rate ($/hour) | B4: ='Start Here'!$B$6 -> 150 | C4: From Start Here
A5: Planning horizon (years) | B5: ='Start Here'!$B$7 -> 15 | C5: From Start Here
A7: Scenario | B7: English Laurel | C7: Boxwood | D7: Photinia | E7: Bradford Pear | F7: Ash: keep treating vs. replace
A8: Unit basis | B8: 100 lf hedge | C8: 50 lf low hedge | D8: 100 lf hedge | E8: per tree | F8: per tree, DBH from Ash EAB
A9: CURRENT MAINTENANCE
A10: Service visits per year | B10: 2 | C10: 3 | D10: 4 | E10: 0.33 | F10: 0
A11: Labor hours per visit | B11: 5 | C11: 2 | D11: 3 | E11: 4 | F11: 0
A12: Other annual cost (injection, spray, replacements) | B12: 0 | C12: 0 | D12: 0 | E12: 0 | F12: ='Ash EAB'!$B$11*'Ash EAB'!$B$16/'Ash EAB'!$B$12 -> 108
A13: Annual cost | B13: =B10*B11*$B$4+B12 -> 1500 | C13: =C10*C11*$B$4+C12 -> 900 | D13: =D10*D11*$B$4+D12 -> 1800 | E13: =E10*E11*$B$4+E12 -> 198 | F13: =F10*F11*$B$4+F12 -> 108
A14: Cost over horizon | B14: =B13*$B$5 -> 22500 | C14: =C13*$B$5 -> 13500 | D14: =D13*$B$5 -> 27000 | E14: =E13*$B$5 -> 2970 | F14: =F13*$B$5 -> 1620
A15: ONE-TIME CONVERSION COST
A16: Removal labor hours | B16: 20 | C16: 6 | D16: 14 | E16: 8 | F16: 8
A17: Removal labor | B17: =B16*$B$4 -> 3000 | C17: =C16*$B$4 -> 900 | D17: =D16*$B$4 -> 2100 | E17: =E16*$B$4 -> 1200 | F17: =F16*$B$4 -> 1200
A18: Disposal / stump grinding | B18: 800 | C18: 200 | D18: 500 | E18: 400 | F18: 400
A19: Plant quantity | B19: 25 | C19: 17 | D19: 25 | E19: 1 | F19: 1
A20: Stock unit cost | B20: 55 | C20: 45 | D20: 55 | E20: 350 | F20: 350
A21: Install labor hours | B21: 10 | C21: 6 | D21: 10 | E21: 4 | F21: 4
A22: Establishment package, years 1-3 (mulch, checks, formative pruning) | B22: 900 | C22: 500 | D22: 900 | E22: 400 | F22: 400
A23: Hired watering, years 1-3 (0 if the owner waters; from Establishment Water) | B23: 0 | C23: 0 | D23: 0 | E23: 0 | F23: 0
A24: TOTAL CONVERSION COST | B24: =B17+B18+B19*B20+B21*$B$4+B22+B23 -> 7575 | C24: =C17+C18+C19*C20+C21*$B$4+C22+C23 -> 3265 | D24: =D17+D18+D19*D20+D21*$B$4+D22+D23 -> 6375 | E24: =E17+E18+E19*E20+E21*$B$4+E22+E23 -> 2950 | F24: =F17+F18+F19*F20+F21*$B$4+F22+F23 -> 2950
A25: CONVERTED MAINTENANCE
A26: Average visits per year over horizon | B26: 1 | C26: 1 | D26: 1 | E26: 0.33 | F26: 0.33
A27: Labor hours per visit | B27: 4 | C27: 2 | D27: 4 | E27: 2 | F27: 2
A28: Annual cost | B28: =B26*B27*$B$4 -> 600 | C28: =C26*C27*$B$4 -> 300 | D28: =D26*D27*$B$4 -> 600 | E28: =E26*E27*$B$4 -> 99 | F28: =F26*F27*$B$4 -> 99
A29: Cost over horizon | B29: =B28*$B$5 -> 9000 | C29: =C28*$B$5 -> 4500 | D29: =D28*$B$5 -> 9000 | E29: =E28*$B$5 -> 1485 | F29: =F28*$B$5 -> 1485
A30: RESULT
A31: Converted total (incl. conversion) | B31: =B24+B29 -> 16575 | C31: =C24+C29 -> 7765 | D31: =D24+D29 -> 15375 | E31: =E24+E29 -> 4435 | F31: =F24+F29 -> 4435
A32: Net difference vs. status quo (positive = saving) | B32: =B14-B31 -> 5925 | C32: =C14-C31 -> 5735 | D32: =D14-D31 -> 11625 | E32: =E14-E31 -> -1465 | F32: =F14-F31 -> -2815
A33: Annual savings after conversion | B33: =B13-B28 -> 900 | C33: =C13-C28 -> 600 | D33: =D13-D28 -> 1200 | E33: =E13-E28 -> 99 | F33: =F13-F28 -> 9
A34: Simple payback (years) | B34: =IF(B33<=0,"no payback",IF(B24/B33>50,"over 50 yrs",B24/B33)) -> 8.4166667 | C34: =IF(C33<=0,"no payback",IF(C24/C33>50,"over 50 yrs",C24/C33)) -> 5.4416667 | D34: =IF(D33<=0,"no payback",IF(D24/D33>50,"over 50 yrs",D24/D33)) -> 5.3125 | E34: =IF(E33<=0,"no payback",IF(E24/E33>50,"over 50 yrs",E24/E33)) -> 29.79798 | F34: =IF(F33<=0,"no payback",IF(F24/F33>50,"over 50 yrs",F24/F33)) -> over 50 yrs
A35: REMOVE SOON ONLY — COST OF WAITING
A36: Emergency removal cost if deferred | B36: 0 | C36: 0 | D36: 0 | E36: 2400 | F36: ='Ash EAB'!$B$16*'Ash EAB'!$B$13*'Ash EAB'!$B$14 -> 2160
A37: Planned removal saves | B37: =IF(B36=0,"n/a (optional)",B36-(B17+B18)) -> n/a (optional) | C37: =IF(C36=0,"n/a (optional)",C36-(C17+C18)) -> n/a (optional) | D37: =IF(D36=0,"n/a (optional)",D36-(D17+D18)) -> n/a (optional) | E37: =IF(E36=0,"n/a (optional)",E36-(E17+E18)) -> 800 | F37: =IF(F36=0,"n/a (optional)",F36-(F17+F18)) -> 560
A39: WHAT THIS SHOWS
A40: HEDGES PAY BACK. Boxwood, photinia and laurel pay back inside a decade on maintenance savings alone, because repeated shearing and spray visits leave the schedule. Shearing frequency, not plant size, drives the bill.
A41: SINGLE TREES MOSTLY DO NOT. Bradford pear runs about 30 years. One tree does not need enough recurring work to pay for its own replacement. Do not justify it on cost.
A42: For trees, the cost of waiting is the reason. A planned removal is scheduled, budgeted and safe. A storm-failed pear or a brittle EAB-killed ash is an emergency, with more rigging and possible property damage.
A43: ASH: at about $12 per inch every 2 years, an 18 in ash costs about $108 a year to treat, so replacement does not pay back on cost. Treating a healthy, high-value ash is the cheaper choice and keeps the canopy. Replace low-value or declining ash, on timing and safety grounds. Use the Ash Register for each tree.
A44: Adding hired watering raises the conversion cost and lengthens the payback. Include it anyway. It is the cost of good survival.

Sheet Install Log
A1: Install ID | B1: Install Date | C1: Owner / Address | D1: Soil Grp | E1: Aspect | F1: Legacy Plant Replaced | G1: Species Installed (dropdown) | H1: Tier (auto) | I1: Stock Size | J1: Qty Planted | K1: Water By | L1: Yr 1 | M1: Yr 2 | N1: Yr 3 | O1: Yr 5 | P1: Yr 10 | Q1: Next Score Due (auto) | R1: Qty Alive | S1: Failure Cause | T1: Notes | U1: GIS Point ID
A2: EX-001 | B2: 46330 | C2: EXAMPLE — 1420 Willamette St | D2: 1 | E2: S | F2: English laurel (100 lf) | G2: Morella californica | H2: =IF(G2="","",IFERROR(INDEX(Palette!$K$2:$K$151,MATCH(G2,Palette!$A$2:$A$151,0)),"NOT IN PALETTE")) -> A | I2: 5 gal | J2: 25 | K2: Owner | L2: 4 | M2: 4 | N2: 5 | Q2: =IF(OR(B2="",G2=""),"",IF(AND(R2<>"",R2=0),"closed",IF(L2="",EDATE(B2,12),IF(M2="",EDATE(B2,24),IF(N2="",EDATE(B2,36),IF(O2="",EDATE(B2,60),IF(P2="",EDATE(B2,120),"done"))))))) -> 48156 | R2: 23 | S2: Winter-wet / root rot | T2: Two losses at wet north end; replaced yr 2 | U2: PT-0001
H3: =IF(G3="","",IFERROR(INDEX(Palette!$K$2:$K$151,MATCH(G3,Palette!$A$2:$A$151,0)),"NOT IN PALETTE")) | Q3: =IF(OR(B3="",G3=""),"",IF(AND(R3<>"",R3=0),"closed",IF(L3="",EDATE(B3,12),IF(M3="",EDATE(B3,24),IF(N3="",EDATE(B3,36),IF(O3="",EDATE(B3,60),IF(P3="",EDATE(B3,120),"done")))))))
H4: =IF(G4="","",IFERROR(INDEX(Palette!$K$2:$K$151,MATCH(G4,Palette!$A$2:$A$151,0)),"NOT IN PALETTE")) | Q4: =IF(OR(B4="",G4=""),"",IF(AND(R4<>"",R4=0),"closed",IF(L4="",EDATE(B4,12),IF(M4="",EDATE(B4,24),IF(N4="",EDATE(B4,36),IF(O4="",EDATE(B4,60),IF(P4="",EDATE(B4,120),"done")))))))
H5: =IF(G5="","",IFERROR(INDEX(Palette!$K$2:$K$151,MATCH(G5,Palette!$A$2:$A$151,0)),"NOT IN PALETTE")) | Q5: =IF(OR(B5="",G5=""),"",IF(AND(R5<>"",R5=0),"closed",IF(L5="",EDATE(B5,12),IF(M5="",EDATE(B5,24),IF(N5="",EDATE(B5,36),IF(O5="",EDATE(B5,60),IF(P5="",EDATE(B5,120),"done")))))))
H6: =IF(G6="","",IFERROR(INDEX(Palette!$K$2:$K$151,MATCH(G6,Palette!$A$2:$A$151,0)),"NOT IN PALETTE")) | Q6: =IF(OR(B6="",G6=""),"",IF(AND(R6<>"",R6=0),"closed",IF(L6="",EDATE(B6,12),IF(M6="",EDATE(B6,24),IF(N6="",EDATE(B6,36),IF(O6="",EDATE(B6,60),IF(P6="",EDATE(B6,120),"done")))))))
H7: =IF(G7="","",IFERROR(INDEX(Palette!$K$2:$K$151,MATCH(G7,Palette!$A$2:$A$151,0)),"NOT IN PALETTE")) | Q7: =IF(OR(B7="",G7=""),"",IF(AND(R7<>"",R7=0),"closed",IF(L7="",EDATE(B7,12),IF(M7="",EDATE(B7,24),IF(N7="",EDATE(B7,36),IF(O7="",EDATE(B7,60),IF(P7="",EDATE(B7,120),"done")))))))
H8: =IF(G8="","",IFERROR(INDEX(Palette!$K$2:$K$151,MATCH(G8,Palette!$A$2:$A$151,0)),"NOT IN PALETTE")) | Q8: =IF(OR(B8="",G8=""),"",IF(AND(R8<>"",R8=0),"closed",IF(L8="",EDATE(B8,12),IF(M8="",EDATE(B8,24),IF(N8="",EDATE(B8,36),IF(O8="",EDATE(B8,60),IF(P8="",EDATE(B8,120),"done")))))))
H9: =IF(G9="","",IFERROR(INDEX(Palette!$K$2:$K$151,MATCH(G9,Palette!$A$2:$A$151,0)),"NOT IN PALETTE")) | Q9: =IF(OR(B9="",G9=""),"",IF(AND(R9<>"",R9=0),"closed",IF(L9="",EDATE(B9,12),IF(M9="",EDATE(B9,24),IF(N9="",EDATE(B9,36),IF(O9="",EDATE(B9,60),IF(P9="",EDATE(B9,120),"done")))))))
H10: =IF(G10="","",IFERROR(INDEX(Palette!$K$2:$K$151,MATCH(G10,Palette!$A$2:$A$151,0)),"NOT IN PALETTE")) | Q10: =IF(OR(B10="",G10=""),"",IF(AND(R10<>"",R10=0),"closed",IF(L10="",EDATE(B10,12),IF(M10="",EDATE(B10,24),IF(N10="",EDATE(B10,36),IF(O10="",EDATE(B10,60),IF(P10="",EDATE(B10,120),"done")))))))
H11: =IF(G11="","",IFERROR(INDEX(Palette!$K$2:$K$151,MATCH(G11,Palette!$A$2:$A$151,0)),"NOT IN PALETTE")) | Q11: =IF(OR(B11="",G11=""),"",IF(AND(R11<>"",R11=0),"closed",IF(L11="",EDATE(B11,12),IF(M11="",EDATE(B11,24),IF(N11="",EDATE(B11,36),IF(O11="",EDATE(B11,60),IF(P11="",EDATE(B11,120),"done")))))))
H12: =IF(G12="","",IFERROR(INDEX(Palette!$K$2:$K$151,MATCH(G12,Palette!$A$2:$A$151,0)),"NOT IN PALETTE")) | Q12: =IF(OR(B12="",G12=""),"",IF(AND(R12<>"",R12=0),"closed",IF(L12="",EDATE(B12,12),IF(M12="",EDATE(B12,24),IF(N12="",EDATE(B12,36),IF(O12="",EDATE(B12,60),IF(P12="",EDATE(B12,120),"done")))))))
H13: =IF(G13="","",IFERROR(INDEX(Palette!$K$2:$K$151,MATCH(G13,Palette!$A$2:$A$151,0)),"NOT IN PALETTE")) | Q13: =IF(OR(B13="",G13=""),"",IF(AND(R13<>"",R13=0),"closed",IF(L13="",EDATE(B13,12),IF(M13="",EDATE(B13,24),IF(N13="",EDATE(B13,36),IF(O13="",EDATE(B13,60),IF(P13="",EDATE(B13,120),"done")))))))
H14: =IF(G14="","",IFERROR(INDEX(Palette!$K$2:$K$151,MATCH(G14,Palette!$A$2:$A$151,0)),"NOT IN PALETTE")) | Q14: =IF(OR(B14="",G14=""),"",IF(AND(R14<>"",R14=0),"closed",IF(L14="",EDATE(B14,12),IF(M14="",EDATE(B14,24),IF(N14="",EDATE(B14,36),IF(O14="",EDATE(B14,60),IF(P14="",EDATE(B14,120),"done")))))))
... H202: =IF(G202="","",IFERROR(INDEX(Palette!$K$2:$K$151,MATCH(G202,Palette!$A$2:$A$151,0)),"NOT IN PALETTE")) | Q202: =IF(OR(B202="",G202=""),"",IF(AND(R202<>"",R202=0),"closed",IF(L202="",EDATE(B202,12),IF(M202="",EDATE(B202,24),IF(N202="",EDATE(B202,36),IF(O202="",EDATE(B202,60),IF(P202="",EDATE(B202,120),"done")))))))
A204: Condition scale: 5 = vigorous, no action needed · 4 = healthy, minor issues · 3 = established but stressed (note cause) · 2 = declining, action required · 1 = failing or dead.
A205: One row per species per site. Enter Qty Alive = Qty Planted on install day, then update it at each visit. Next Score Due turns amber within 60 days and red when overdue.
A206: Delete the orange example row before use. Totals and reviews start at row 3, so the example never counts.

Sheet Ash Register
A1: Tree ID | B1: Date Assessed | C1: Owner / Address | D1: DBH (in) | E1: Canopy Dieback % | F1: EAB Signs (Y/N) | G1: Tree Value | H1: Site Type | I1: Near Target (Y/N) | J1: Recommendation (auto) | K1: Replace With (auto) | L1: Treat Cost per Cycle (auto) | M1: Treat Cost over Horizon (auto) | N1: Planned Remove + Replace (auto) | O1: Emergency Remove + Replace (auto) | P1: Cheaper over Horizon (auto) | Q1: Action Taken | R1: Last Treated | S1: Next Treatment Due (auto) | T1: Successor Install ID | U1: Notes
A2: EX-A1 | B2: 46301 | C2: EXAMPLE — 88 Oak St | D2: 18 | E2: 0.1 | F2: N | G2: High | H2: Wet | I2: Y | J2: =IF(N(D2)=0,"",IF(N(E2)>0.5,IF(I2="Y","REMOVE NOW: target at risk","REMOVE NOW"),IF(N(E2)>=0.3,"GRAY ZONE: assess structure",IF(G2="High","TREAT",IF(F2="Y","REMOVE AND REPLACE","PLANT FIRST, REMOVE LATER"))))) -> TREAT | K2: =IF(N(D2)=0,"",IF(J2="TREAT","Successor if space: ","")&IF(H2="Wet","Quercus bicolor or Malus fusca",IF(H2="Riparian","Natives only: Malus fusca, Salix, Q. garryana on edges",IF(H2="Upland","Quercus garryana or Q. macrocarpa","Set site type")))) -> Successor if space: Quercus bicolor or Malus fusca | L2: =IF(N(D2)=0,"",D2*'Ash EAB'!$B$11) -> 216 | M2: =IF(N(D2)=0,"",L2*ROUNDUP('Ash EAB'!$B$17/'Ash EAB'!$B$12,0)) -> 1728 | N2: =IF(N(D2)=0,"",D2*'Ash EAB'!$B$13+'Ash EAB'!$B$15) -> 2790 | O2: =IF(N(D2)=0,"",D2*'Ash EAB'!$B$13*'Ash EAB'!$B$14+'Ash EAB'!$B$15) -> 3510 | P2: =IF(N(D2)=0,"",IF(M2<N2,"Treat","Replace")) -> Treat | Q2: Treated | R2: 46174 | S2: =IF(R2="","",EDATE(R2,ROUND('Ash EAB'!$B$12*12,0))) -> 46905 | U2: Street-side shade tree; owner wants to keep it
J3: =IF(N(D3)=0,"",IF(N(E3)>0.5,IF(I3="Y","REMOVE NOW: target at risk","REMOVE NOW"),IF(N(E3)>=0.3,"GRAY ZONE: assess structure",IF(G3="High","TREAT",IF(F3="Y","REMOVE AND REPLACE","PLANT FIRST, REMOVE LATER"))))) | K3: =IF(N(D3)=0,"",IF(J3="TREAT","Successor if space: ","")&IF(H3="Wet","Quercus bicolor or Malus fusca",IF(H3="Riparian","Natives only: Malus fusca, Salix, Q. garryana on edges",IF(H3="Upland","Quercus garryana or Q. macrocarpa","Set site type")))) | L3: =IF(N(D3)=0,"",D3*'Ash EAB'!$B$11) | M3: =IF(N(D3)=0,"",L3*ROUNDUP('Ash EAB'!$B$17/'Ash EAB'!$B$12,0)) | N3: =IF(N(D3)=0,"",D3*'Ash EAB'!$B$13+'Ash EAB'!$B$15) | O3: =IF(N(D3)=0,"",D3*'Ash EAB'!$B$13*'Ash EAB'!$B$14+'Ash EAB'!$B$15) | P3: =IF(N(D3)=0,"",IF(M3<N3,"Treat","Replace")) | S3: =IF(R3="","",EDATE(R3,ROUND('Ash EAB'!$B$12*12,0)))
J4: =IF(N(D4)=0,"",IF(N(E4)>0.5,IF(I4="Y","REMOVE NOW: target at risk","REMOVE NOW"),IF(N(E4)>=0.3,"GRAY ZONE: assess structure",IF(G4="High","TREAT",IF(F4="Y","REMOVE AND REPLACE","PLANT FIRST, REMOVE LATER"))))) | K4: =IF(N(D4)=0,"",IF(J4="TREAT","Successor if space: ","")&IF(H4="Wet","Quercus bicolor or Malus fusca",IF(H4="Riparian","Natives only: Malus fusca, Salix, Q. garryana on edges",IF(H4="Upland","Quercus garryana or Q. macrocarpa","Set site type")))) | L4: =IF(N(D4)=0,"",D4*'Ash EAB'!$B$11) | M4: =IF(N(D4)=0,"",L4*ROUNDUP('Ash EAB'!$B$17/'Ash EAB'!$B$12,0)) | N4: =IF(N(D4)=0,"",D4*'Ash EAB'!$B$13+'Ash EAB'!$B$15) | O4: =IF(N(D4)=0,"",D4*'Ash EAB'!$B$13*'Ash EAB'!$B$14+'Ash EAB'!$B$15) | P4: =IF(N(D4)=0,"",IF(M4<N4,"Treat","Replace")) | S4: =IF(R4="","",EDATE(R4,ROUND('Ash EAB'!$B$12*12,0)))
J5: =IF(N(D5)=0,"",IF(N(E5)>0.5,IF(I5="Y","REMOVE NOW: target at risk","REMOVE NOW"),IF(N(E5)>=0.3,"GRAY ZONE: assess structure",IF(G5="High","TREAT",IF(F5="Y","REMOVE AND REPLACE","PLANT FIRST, REMOVE LATER"))))) | K5: =IF(N(D5)=0,"",IF(J5="TREAT","Successor if space: ","")&IF(H5="Wet","Quercus bicolor or Malus fusca",IF(H5="Riparian","Natives only: Malus fusca, Salix, Q. garryana on edges",IF(H5="Upland","Quercus garryana or Q. macrocarpa","Set site type")))) | L5: =IF(N(D5)=0,"",D5*'Ash EAB'!$B$11) | M5: =IF(N(D5)=0,"",L5*ROUNDUP('Ash EAB'!$B$17/'Ash EAB'!$B$12,0)) | N5: =IF(N(D5)=0,"",D5*'Ash EAB'!$B$13+'Ash EAB'!$B$15) | O5: =IF(N(D5)=0,"",D5*'Ash EAB'!$B$13*'Ash EAB'!$B$14+'Ash EAB'!$B$15) | P5: =IF(N(D5)=0,"",IF(M5<N5,"Treat","Replace")) | S5: =IF(R5="","",EDATE(R5,ROUND('Ash EAB'!$B$12*12,0)))
J6: =IF(N(D6)=0,"",IF(N(E6)>0.5,IF(I6="Y","REMOVE NOW: target at risk","REMOVE NOW"),IF(N(E6)>=0.3,"GRAY ZONE: assess structure",IF(G6="High","TREAT",IF(F6="Y","REMOVE AND REPLACE","PLANT FIRST, REMOVE LATER"))))) | K6: =IF(N(D6)=0,"",IF(J6="TREAT","Successor if space: ","")&IF(H6="Wet","Quercus bicolor or Malus fusca",IF(H6="Riparian","Natives only: Malus fusca, Salix, Q. garryana on edges",IF(H6="Upland","Quercus garryana or Q. macrocarpa","Set site type")))) | L6: =IF(N(D6)=0,"",D6*'Ash EAB'!$B$11) | M6: =IF(N(D6)=0,"",L6*ROUNDUP('Ash EAB'!$B$17/'Ash EAB'!$B$12,0)) | N6: =IF(N(D6)=0,"",D6*'Ash EAB'!$B$13+'Ash EAB'!$B$15) | O6: =IF(N(D6)=0,"",D6*'Ash EAB'!$B$13*'Ash EAB'!$B$14+'Ash EAB'!$B$15) | P6: =IF(N(D6)=0,"",IF(M6<N6,"Treat","Replace")) | S6: =IF(R6="","",EDATE(R6,ROUND('Ash EAB'!$B$12*12,0)))
J7: =IF(N(D7)=0,"",IF(N(E7)>0.5,IF(I7="Y","REMOVE NOW: target at risk","REMOVE NOW"),IF(N(E7)>=0.3,"GRAY ZONE: assess structure",IF(G7="High","TREAT",IF(F7="Y","REMOVE AND REPLACE","PLANT FIRST, REMOVE LATER"))))) | K7: =IF(N(D7)=0,"",IF(J7="TREAT","Successor if space: ","")&IF(H7="Wet","Quercus bicolor or Malus fusca",IF(H7="Riparian","Natives only: Malus fusca, Salix, Q. garryana on edges",IF(H7="Upland","Quercus garryana or Q. macrocarpa","Set site type")))) | L7: =IF(N(D7)=0,"",D7*'Ash EAB'!$B$11) | M7: =IF(N(D7)=0,"",L7*ROUNDUP('Ash EAB'!$B$17/'Ash EAB'!$B$12,0)) | N7: =IF(N(D7)=0,"",D7*'Ash EAB'!$B$13+'Ash EAB'!$B$15) | O7: =IF(N(D7)=0,"",D7*'Ash EAB'!$B$13*'Ash EAB'!$B$14+'Ash EAB'!$B$15) | P7: =IF(N(D7)=0,"",IF(M7<N7,"Treat","Replace")) | S7: =IF(R7="","",EDATE(R7,ROUND('Ash EAB'!$B$12*12,0)))
J8: =IF(N(D8)=0,"",IF(N(E8)>0.5,IF(I8="Y","REMOVE NOW: target at risk","REMOVE NOW"),IF(N(E8)>=0.3,"GRAY ZONE: assess structure",IF(G8="High","TREAT",IF(F8="Y","REMOVE AND REPLACE","PLANT FIRST, REMOVE LATER"))))) | K8: =IF(N(D8)=0,"",IF(J8="TREAT","Successor if space: ","")&IF(H8="Wet","Quercus bicolor or Malus fusca",IF(H8="Riparian","Natives only: Malus fusca, Salix, Q. garryana on edges",IF(H8="Upland","Quercus garryana or Q. macrocarpa","Set site type")))) | L8: =IF(N(D8)=0,"",D8*'Ash EAB'!$B$11) | M8: =IF(N(D8)=0,"",L8*ROUNDUP('Ash EAB'!$B$17/'Ash EAB'!$B$12,0)) | N8: =IF(N(D8)=0,"",D8*'Ash EAB'!$B$13+'Ash EAB'!$B$15) | O8: =IF(N(D8)=0,"",D8*'Ash EAB'!$B$13*'Ash EAB'!$B$14+'Ash EAB'!$B$15) | P8: =IF(N(D8)=0,"",IF(M8<N8,"Treat","Replace")) | S8: =IF(R8="","",EDATE(R8,ROUND('Ash EAB'!$B$12*12,0)))
J9: =IF(N(D9)=0,"",IF(N(E9)>0.5,IF(I9="Y","REMOVE NOW: target at risk","REMOVE NOW"),IF(N(E9)>=0.3,"GRAY ZONE: assess structure",IF(G9="High","TREAT",IF(F9="Y","REMOVE AND REPLACE","PLANT FIRST, REMOVE LATER"))))) | K9: =IF(N(D9)=0,"",IF(J9="TREAT","Successor if space: ","")&IF(H9="Wet","Quercus bicolor or Malus fusca",IF(H9="Riparian","Natives only: Malus fusca, Salix, Q. garryana on edges",IF(H9="Upland","Quercus garryana or Q. macrocarpa","Set site type")))) | L9: =IF(N(D9)=0,"",D9*'Ash EAB'!$B$11) | M9: =IF(N(D9)=0,"",L9*ROUNDUP('Ash EAB'!$B$17/'Ash EAB'!$B$12,0)) | N9: =IF(N(D9)=0,"",D9*'Ash EAB'!$B$13+'Ash EAB'!$B$15) | O9: =IF(N(D9)=0,"",D9*'Ash EAB'!$B$13*'Ash EAB'!$B$14+'Ash EAB'!$B$15) | P9: =IF(N(D9)=0,"",IF(M9<N9,"Treat","Replace")) | S9: =IF(R9="","",EDATE(R9,ROUND('Ash EAB'!$B$12*12,0)))
J10: =IF(N(D10)=0,"",IF(N(E10)>0.5,IF(I10="Y","REMOVE NOW: target at risk","REMOVE NOW"),IF(N(E10)>=0.3,"GRAY ZONE: assess structure",IF(G10="High","TREAT",IF(F10="Y","REMOVE AND REPLACE","PLANT FIRST, REMOVE LATER"))))) | K10: =IF(N(D10)=0,"",IF(J10="TREAT","Successor if space: ","")&IF(H10="Wet","Quercus bicolor or Malus fusca",IF(H10="Riparian","Natives only: Malus fusca, Salix, Q. garryana on edges",IF(H10="Upland","Quercus garryana or Q. macrocarpa","Set site type")))) | L10: =IF(N(D10)=0,"",D10*'Ash EAB'!$B$11) | M10: =IF(N(D10)=0,"",L10*ROUNDUP('Ash EAB'!$B$17/'Ash EAB'!$B$12,0)) | N10: =IF(N(D10)=0,"",D10*'Ash EAB'!$B$13+'Ash EAB'!$B$15) | O10: =IF(N(D10)=0,"",D10*'Ash EAB'!$B$13*'Ash EAB'!$B$14+'Ash EAB'!$B$15) | P10: =IF(N(D10)=0,"",IF(M10<N10,"Treat","Replace")) | S10: =IF(R10="","",EDATE(R10,ROUND('Ash EAB'!$B$12*12,0)))
J11: =IF(N(D11)=0,"",IF(N(E11)>0.5,IF(I11="Y","REMOVE NOW: target at risk","REMOVE NOW"),IF(N(E11)>=0.3,"GRAY ZONE: assess structure",IF(G11="High","TREAT",IF(F11="Y","REMOVE AND REPLACE","PLANT FIRST, REMOVE LATER"))))) | K11: =IF(N(D11)=0,"",IF(J11="TREAT","Successor if space: ","")&IF(H11="Wet","Quercus bicolor or Malus fusca",IF(H11="Riparian","Natives only: Malus fusca, Salix, Q. garryana on edges",IF(H11="Upland","Quercus garryana or Q. macrocarpa","Set site type")))) | L11: =IF(N(D11)=0,"",D11*'Ash EAB'!$B$11) | M11: =IF(N(D11)=0,"",L11*ROUNDUP('Ash EAB'!$B$17/'Ash EAB'!$B$12,0)) | N11: =IF(N(D11)=0,"",D11*'Ash EAB'!$B$13+'Ash EAB'!$B$15) | O11: =IF(N(D11)=0,"",D11*'Ash EAB'!$B$13*'Ash EAB'!$B$14+'Ash EAB'!$B$15) | P11: =IF(N(D11)=0,"",IF(M11<N11,"Treat","Replace")) | S11: =IF(R11="","",EDATE(R11,ROUND('Ash EAB'!$B$12*12,0)))
J12: =IF(N(D12)=0,"",IF(N(E12)>0.5,IF(I12="Y","REMOVE NOW: target at risk","REMOVE NOW"),IF(N(E12)>=0.3,"GRAY ZONE: assess structure",IF(G12="High","TREAT",IF(F12="Y","REMOVE AND REPLACE","PLANT FIRST, REMOVE LATER"))))) | K12: =IF(N(D12)=0,"",IF(J12="TREAT","Successor if space: ","")&IF(H12="Wet","Quercus bicolor or Malus fusca",IF(H12="Riparian","Natives only: Malus fusca, Salix, Q. garryana on edges",IF(H12="Upland","Quercus garryana or Q. macrocarpa","Set site type")))) | L12: =IF(N(D12)=0,"",D12*'Ash EAB'!$B$11) | M12: =IF(N(D12)=0,"",L12*ROUNDUP('Ash EAB'!$B$17/'Ash EAB'!$B$12,0)) | N12: =IF(N(D12)=0,"",D12*'Ash EAB'!$B$13+'Ash EAB'!$B$15) | O12: =IF(N(D12)=0,"",D12*'Ash EAB'!$B$13*'Ash EAB'!$B$14+'Ash EAB'!$B$15) | P12: =IF(N(D12)=0,"",IF(M12<N12,"Treat","Replace")) | S12: =IF(R12="","",EDATE(R12,ROUND('Ash EAB'!$B$12*12,0)))
J13: =IF(N(D13)=0,"",IF(N(E13)>0.5,IF(I13="Y","REMOVE NOW: target at risk","REMOVE NOW"),IF(N(E13)>=0.3,"GRAY ZONE: assess structure",IF(G13="High","TREAT",IF(F13="Y","REMOVE AND REPLACE","PLANT FIRST, REMOVE LATER"))))) | K13: =IF(N(D13)=0,"",IF(J13="TREAT","Successor if space: ","")&IF(H13="Wet","Quercus bicolor or Malus fusca",IF(H13="Riparian","Natives only: Malus fusca, Salix, Q. garryana on edges",IF(H13="Upland","Quercus garryana or Q. macrocarpa","Set site type")))) | L13: =IF(N(D13)=0,"",D13*'Ash EAB'!$B$11) | M13: =IF(N(D13)=0,"",L13*ROUNDUP('Ash EAB'!$B$17/'Ash EAB'!$B$12,0)) | N13: =IF(N(D13)=0,"",D13*'Ash EAB'!$B$13+'Ash EAB'!$B$15) | O13: =IF(N(D13)=0,"",D13*'Ash EAB'!$B$13*'Ash EAB'!$B$14+'Ash EAB'!$B$15) | P13: =IF(N(D13)=0,"",IF(M13<N13,"Treat","Replace")) | S13: =IF(R13="","",EDATE(R13,ROUND('Ash EAB'!$B$12*12,0)))
J14: =IF(N(D14)=0,"",IF(N(E14)>0.5,IF(I14="Y","REMOVE NOW: target at risk","REMOVE NOW"),IF(N(E14)>=0.3,"GRAY ZONE: assess structure",IF(G14="High","TREAT",IF(F14="Y","REMOVE AND REPLACE","PLANT FIRST, REMOVE LATER"))))) | K14: =IF(N(D14)=0,"",IF(J14="TREAT","Successor if space: ","")&IF(H14="Wet","Quercus bicolor or Malus fusca",IF(H14="Riparian","Natives only: Malus fusca, Salix, Q. garryana on edges",IF(H14="Upland","Quercus garryana or Q. macrocarpa","Set site type")))) | L14: =IF(N(D14)=0,"",D14*'Ash EAB'!$B$11) | M14: =IF(N(D14)=0,"",L14*ROUNDUP('Ash EAB'!$B$17/'Ash EAB'!$B$12,0)) | N14: =IF(N(D14)=0,"",D14*'Ash EAB'!$B$13+'Ash EAB'!$B$15) | O14: =IF(N(D14)=0,"",D14*'Ash EAB'!$B$13*'Ash EAB'!$B$14+'Ash EAB'!$B$15) | P14: =IF(N(D14)=0,"",IF(M14<N14,"Treat","Replace")) | S14: =IF(R14="","",EDATE(R14,ROUND('Ash EAB'!$B$12*12,0)))
... J302: =IF(N(D302)=0,"",IF(N(E302)>0.5,IF(I302="Y","REMOVE NOW: target at risk","REMOVE NOW"),IF(N(E302)>=0.3,"GRAY ZONE: assess structure",IF(G302="High","TREAT",IF(F302="Y","REMOVE AND REPLACE","PLANT FIRST, REMOVE LATER"))))) | K302: =IF(N(D302)=0,"",IF(J302="TREAT","Successor if space: ","")&IF(H302="Wet","Quercus bicolor or Malus fusca",IF(H302="Riparian","Natives only: Malus fusca, Salix, Q. garryana on edges",IF(H302="Upland","Quercus garryana or Q. macrocarpa","Set site type")))) | L302: =IF(N(D302)=0,"",D302*'Ash EAB'!$B$11) | M302: =IF(N(D302)=0,"",L302*ROUNDUP('Ash EAB'!$B$17/'Ash EAB'!$B$12,0)) | N302: =IF(N(D302)=0,"",D302*'Ash EAB'!$B$13+'Ash EAB'!$B$15) | O302: =IF(N(D302)=0,"",D302*'Ash EAB'!$B$13*'Ash EAB'!$B$14+'Ash EAB'!$B$15) | P302: =IF(N(D302)=0,"",IF(M302<N302,"Treat","Replace")) | S302: =IF(R302="","",EDATE(R302,ROUND('Ash EAB'!$B$12*12,0)))
A304: One row per ash tree. Enter DBH, dieback (as a percent), signs, value, site and target. The recommendation, replacement and costs fill in from the rules and prices on the Ash EAB tab.
A305: When a tree is treated, enter the date in Last Treated. Next Treatment Due turns amber within 60 days and red when overdue.
A306: Delete the orange example row before use. Summaries on the Ash EAB tab start at row 3, so the example never counts.

Sheet Program Review
A1: PROGRAM REVIEW — SURVIVAL AND DIVERSITY
A2: Everything here updates from the Install Log and the Palette. Nothing to type. Review it each August, before fall orders (workflow W6).
A4: OVERALL
A5: Install Log rows used | B5: =COUNTA('Install Log'!$G$3:$G$202) -> 0
A6: Plants planted | B6: =SUM('Install Log'!$J$3:$J$202) -> 0
A7: Plants with a current count | B7: =SUMIFS('Install Log'!$J$3:$J$202,'Install Log'!$R$3:$R$202,"<>") -> 0
A8: Plants alive | B8: =SUM('Install Log'!$R$3:$R$202) -> 0
A9: Survival rate (counted plants) | B9: =IF(B7=0,"—",B8/B7) -> —
A10: Rows with a species not in the Palette | B10: =COUNTIF('Install Log'!$H$3:$H$202,"NOT IN PALETTE") -> 0
A11: Tier B share of all plants | B11: =IF(B6=0,"—",SUMIF('Install Log'!$H$3:$H$202,"B",'Install Log'!$J$3:$J$202)/B6) -> —
A12: Tier C or Reject plants planted (should be 0) | B12: =SUMIF('Install Log'!$H$3:$H$202,"C",'Install Log'!$J$3:$J$202)+SUMIF('Install Log'!$H$3:$H$202,"Reject",'Install Log'!$J$3:$J$202) -> 0
A13: Rows with a score overdue | B13: =COUNTIFS('Install Log'!$Q$3:$Q$202,"<"&TODAY()) -> 0
A15: BY SOIL GROUP
A16: Group | B16: Planted | C16: Counted | D16: Alive | E16: Survival
A17: Group 1 | B17: =SUMIF('Install Log'!$D$3:$D$202,1,'Install Log'!$J$3:$J$202) -> 0 | C17: =SUMIFS('Install Log'!$J$3:$J$202,'Install Log'!$D$3:$D$202,1,'Install Log'!$R$3:$R$202,"<>") -> 0 | D17: =SUMIF('Install Log'!$D$3:$D$202,1,'Install Log'!$R$3:$R$202) -> 0 | E17: =IF(C17=0,"—",D17/C17) -> —
A18: Group 2 | B18: =SUMIF('Install Log'!$D$3:$D$202,2,'Install Log'!$J$3:$J$202) -> 0 | C18: =SUMIFS('Install Log'!$J$3:$J$202,'Install Log'!$D$3:$D$202,2,'Install Log'!$R$3:$R$202,"<>") -> 0 | D18: =SUMIF('Install Log'!$D$3:$D$202,2,'Install Log'!$R$3:$R$202) -> 0 | E18: =IF(C18=0,"—",D18/C18) -> —
A19: Group 3 | B19: =SUMIF('Install Log'!$D$3:$D$202,3,'Install Log'!$J$3:$J$202) -> 0 | C19: =SUMIFS('Install Log'!$J$3:$J$202,'Install Log'!$D$3:$D$202,3,'Install Log'!$R$3:$R$202,"<>") -> 0 | D19: =SUMIF('Install Log'!$D$3:$D$202,3,'Install Log'!$R$3:$R$202) -> 0 | E19: =IF(C19=0,"—",D19/C19) -> —
A21: BY TIER
A22: Tier | B22: Planted | C22: Counted | D22: Alive | E22: Survival
A23: Tier A | B23: =SUMIF('Install Log'!$H$3:$H$202,"A",'Install Log'!$J$3:$J$202) -> 0 | C23: =SUMIFS('Install Log'!$J$3:$J$202,'Install Log'!$H$3:$H$202,"A",'Install Log'!$R$3:$R$202,"<>") -> 0 | D23: =SUMIF('Install Log'!$H$3:$H$202,"A",'Install Log'!$R$3:$R$202) -> 0 | E23: =IF(C23=0,"—",D23/C23) -> —
A24: Tier B | B24: =SUMIF('Install Log'!$H$3:$H$202,"B",'Install Log'!$J$3:$J$202) -> 0 | C24: =SUMIFS('Install Log'!$J$3:$J$202,'Install Log'!$H$3:$H$202,"B",'Install Log'!$R$3:$R$202,"<>") -> 0 | D24: =SUMIF('Install Log'!$H$3:$H$202,"B",'Install Log'!$R$3:$R$202) -> 0 | E24: =IF(C24=0,"—",D24/C24) -> —
A25: Tier C | B25: =SUMIF('Install Log'!$H$3:$H$202,"C",'Install Log'!$J$3:$J$202) -> 0 | C25: =SUMIFS('Install Log'!$J$3:$J$202,'Install Log'!$H$3:$H$202,"C",'Install Log'!$R$3:$R$202,"<>") -> 0 | D25: =SUMIF('Install Log'!$H$3:$H$202,"C",'Install Log'!$R$3:$R$202) -> 0 | E25: =IF(C25=0,"—",D25/C25) -> —
A27: SPECIES, GENUS AND FAMILY — 10-20-30 RULE
A28: Santamour's rule: no single species above 10% of plants, genus above 20%, family above 30%. Flags count only after the minimum plant number in Start Here. This table mirrors the Palette row by row, so new species appear by themselves. Use the filter to sort by Planted.
A29: Species | B29: Tier | C29: Genus | D29: Family | E29: Planted | F29: Alive | G29: Survival | H29: Species % | I29: Genus % | J29: Family % | K29: Flag
A30: =IF(Palette!$A2="","",Palette!$A2) -> Maclura pomifera 'White Shield' | B30: =IF($A30="","",Palette!$K2) -> A | C30: =IF($A30="","",Palette!$C2) -> Maclura | D30: =IF($A30="","",Palette!$D2) -> Moraceae | E30: =IF($A30="","",SUMIF('Install Log'!$G$3:$G$202,$A30,'Install Log'!$J$3:$J$202)) -> 0 | F30: =IF($A30="","",SUMIF('Install Log'!$G$3:$G$202,$A30,'Install Log'!$R$3:$R$202)) -> 0 | G30: =IF(OR($A30="",N($E30)=0),"",IFERROR($F30/SUMIFS('Install Log'!$J$3:$J$202,'Install Log'!$G$3:$G$202,$A30,'Install Log'!$R$3:$R$202,"<>"),"—")) | H30: =IF(OR($A30="",$B$6=0),"",$E30/$B$6) | I30: =IF(OR($A30="",$B$6=0),"",SUMIF($C$30:$C$179,$C30,$E$30:$E$179)/$B$6) | J30: =IF(OR($A30="",$B$6=0),"",SUMIF($D$30:$D$179,$D30,$E$30:$E$179)/$B$6) | K30: =IF(OR($A30="",N($E30)=0),"",IF($B$6<'Start Here'!$B$10,"too few plants",IF(AND($H30<=0.1,$I30<=0.2,$J30<=0.3),"ok",TRIM(IF($H30>0.1,"SPECIES ","")&IF($I30>0.2,"GENUS ","")&IF($J30>0.3,"FAMILY","")))))
A31: =IF(Palette!$A3="","",Palette!$A3) -> Quercus bicolor | B31: =IF($A31="","",Palette!$K3) -> A | C31: =IF($A31="","",Palette!$C3) -> Quercus | D31: =IF($A31="","",Palette!$D3) -> Fagaceae | E31: =IF($A31="","",SUMIF('Install Log'!$G$3:$G$202,$A31,'Install Log'!$J$3:$J$202)) -> 0 | F31: =IF($A31="","",SUMIF('Install Log'!$G$3:$G$202,$A31,'Install Log'!$R$3:$R$202)) -> 0 | G31: =IF(OR($A31="",N($E31)=0),"",IFERROR($F31/SUMIFS('Install Log'!$J$3:$J$202,'Install Log'!$G$3:$G$202,$A31,'Install Log'!$R$3:$R$202,"<>"),"—")) | H31: =IF(OR($A31="",$B$6=0),"",$E31/$B$6) | I31: =IF(OR($A31="",$B$6=0),"",SUMIF($C$30:$C$179,$C31,$E$30:$E$179)/$B$6) | J31: =IF(OR($A31="",$B$6=0),"",SUMIF($D$30:$D$179,$D31,$E$30:$E$179)/$B$6) | K31: =IF(OR($A31="",N($E31)=0),"",IF($B$6<'Start Here'!$B$10,"too few plants",IF(AND($H31<=0.1,$I31<=0.2,$J31<=0.3),"ok",TRIM(IF($H31>0.1,"SPECIES ","")&IF($I31>0.2,"GENUS ","")&IF($J31>0.3,"FAMILY","")))))
A32: =IF(Palette!$A4="","",Palette!$A4) -> Quercus garryana | B32: =IF($A32="","",Palette!$K4) -> A | C32: =IF($A32="","",Palette!$C4) -> Quercus | D32: =IF($A32="","",Palette!$D4) -> Fagaceae | E32: =IF($A32="","",SUMIF('Install Log'!$G$3:$G$202,$A32,'Install Log'!$J$3:$J$202)) -> 0 | F32: =IF($A32="","",SUMIF('Install Log'!$G$3:$G$202,$A32,'Install Log'!$R$3:$R$202)) -> 0 | G32: =IF(OR($A32="",N($E32)=0),"",IFERROR($F32/SUMIFS('Install Log'!$J$3:$J$202,'Install Log'!$G$3:$G$202,$A32,'Install Log'!$R$3:$R$202,"<>"),"—")) | H32: =IF(OR($A32="",$B$6=0),"",$E32/$B$6) | I32: =IF(OR($A32="",$B$6=0),"",SUMIF($C$30:$C$179,$C32,$E$30:$E$179)/$B$6) | J32: =IF(OR($A32="",$B$6=0),"",SUMIF($D$30:$D$179,$D32,$E$30:$E$179)/$B$6) | K32: =IF(OR($A32="",N($E32)=0),"",IF($B$6<'Start Here'!$B$10,"too few plants",IF(AND($H32<=0.1,$I32<=0.2,$J32<=0.3),"ok",TRIM(IF($H32>0.1,"SPECIES ","")&IF($I32>0.2,"GENUS ","")&IF($J32>0.3,"FAMILY","")))))
A33: =IF(Palette!$A5="","",Palette!$A5) -> Quercus imbricaria | B33: =IF($A33="","",Palette!$K5) -> A | C33: =IF($A33="","",Palette!$C5) -> Quercus | D33: =IF($A33="","",Palette!$D5) -> Fagaceae | E33: =IF($A33="","",SUMIF('Install Log'!$G$3:$G$202,$A33,'Install Log'!$J$3:$J$202)) -> 0 | F33: =IF($A33="","",SUMIF('Install Log'!$G$3:$G$202,$A33,'Install Log'!$R$3:$R$202)) -> 0 | G33: =IF(OR($A33="",N($E33)=0),"",IFERROR($F33/SUMIFS('Install Log'!$J$3:$J$202,'Install Log'!$G$3:$G$202,$A33,'Install Log'!$R$3:$R$202,"<>"),"—")) | H33: =IF(OR($A33="",$B$6=0),"",$E33/$B$6) | I33: =IF(OR($A33="",$B$6=0),"",SUMIF($C$30:$C$179,$C33,$E$30:$E$179)/$B$6) | J33: =IF(OR($A33="",$B$6=0),"",SUMIF($D$30:$D$179,$D33,$E$30:$E$179)/$B$6) | K33: =IF(OR($A33="",N($E33)=0),"",IF($B$6<'Start Here'!$B$10,"too few plants",IF(AND($H33<=0.1,$I33<=0.2,$J33<=0.3),"ok",TRIM(IF($H33>0.1,"SPECIES ","")&IF($I33>0.2,"GENUS ","")&IF($J33>0.3,"FAMILY","")))))
A34: =IF(Palette!$A6="","",Palette!$A6) -> Quercus macrocarpa | B34: =IF($A34="","",Palette!$K6) -> A | C34: =IF($A34="","",Palette!$C6) -> Quercus | D34: =IF($A34="","",Palette!$D6) -> Fagaceae | E34: =IF($A34="","",SUMIF('Install Log'!$G$3:$G$202,$A34,'Install Log'!$J$3:$J$202)) -> 0 | F34: =IF($A34="","",SUMIF('Install Log'!$G$3:$G$202,$A34,'Install Log'!$R$3:$R$202)) -> 0 | G34: =IF(OR($A34="",N($E34)=0),"",IFERROR($F34/SUMIFS('Install Log'!$J$3:$J$202,'Install Log'!$G$3:$G$202,$A34,'Install Log'!$R$3:$R$202,"<>"),"—")) | H34: =IF(OR($A34="",$B$6=0),"",$E34/$B$6) | I34: =IF(OR($A34="",$B$6=0),"",SUMIF($C$30:$C$179,$C34,$E$30:$E$179)/$B$6) | J34: =IF(OR($A34="",$B$6=0),"",SUMIF($D$30:$D$179,$D34,$E$30:$E$179)/$B$6) | K34: =IF(OR($A34="",N($E34)=0),"",IF($B$6<'Start Here'!$B$10,"too few plants",IF(AND($H34<=0.1,$I34<=0.2,$J34<=0.3),"ok",TRIM(IF($H34>0.1,"SPECIES ","")&IF($I34>0.2,"GENUS ","")&IF($J34>0.3,"FAMILY","")))))
A35: =IF(Palette!$A7="","",Palette!$A7) -> Calocedrus decurrens | B35: =IF($A35="","",Palette!$K7) -> A | C35: =IF($A35="","",Palette!$C7) -> Calocedrus | D35: =IF($A35="","",Palette!$D7) -> Cupressaceae | E35: =IF($A35="","",SUMIF('Install Log'!$G$3:$G$202,$A35,'Install Log'!$J$3:$J$202)) -> 0 | F35: =IF($A35="","",SUMIF('Install Log'!$G$3:$G$202,$A35,'Install Log'!$R$3:$R$202)) -> 0 | G35: =IF(OR($A35="",N($E35)=0),"",IFERROR($F35/SUMIFS('Install Log'!$J$3:$J$202,'Install Log'!$G$3:$G$202,$A35,'Install Log'!$R$3:$R$202,"<>"),"—")) | H35: =IF(OR($A35="",$B$6=0),"",$E35/$B$6) | I35: =IF(OR($A35="",$B$6=0),"",SUMIF($C$30:$C$179,$C35,$E$30:$E$179)/$B$6) | J35: =IF(OR($A35="",$B$6=0),"",SUMIF($D$30:$D$179,$D35,$E$30:$E$179)/$B$6) | K35: =IF(OR($A35="",N($E35)=0),"",IF($B$6<'Start Here'!$B$10,"too few plants",IF(AND($H35<=0.1,$I35<=0.2,$J35<=0.3),"ok",TRIM(IF($H35>0.1,"SPECIES ","")&IF($I35>0.2,"GENUS ","")&IF($J35>0.3,"FAMILY","")))))
A36: =IF(Palette!$A8="","",Palette!$A8) -> Pinus ponderosa | B36: =IF($A36="","",Palette!$K8) -> A | C36: =IF($A36="","",Palette!$C8) -> Pinus | D36: =IF($A36="","",Palette!$D8) -> Pinaceae | E36: =IF($A36="","",SUMIF('Install Log'!$G$3:$G$202,$A36,'Install Log'!$J$3:$J$202)) -> 0 | F36: =IF($A36="","",SUMIF('Install Log'!$G$3:$G$202,$A36,'Install Log'!$R$3:$R$202)) -> 0 | G36: =IF(OR($A36="",N($E36)=0),"",IFERROR($F36/SUMIFS('Install Log'!$J$3:$J$202,'Install Log'!$G$3:$G$202,$A36,'Install Log'!$R$3:$R$202,"<>"),"—")) | H36: =IF(OR($A36="",$B$6=0),"",$E36/$B$6) | I36: =IF(OR($A36="",$B$6=0),"",SUMIF($C$30:$C$179,$C36,$E$30:$E$179)/$B$6) | J36: =IF(OR($A36="",$B$6=0),"",SUMIF($D$30:$D$179,$D36,$E$30:$E$179)/$B$6) | K36: =IF(OR($A36="",N($E36)=0),"",IF($B$6<'Start Here'!$B$10,"too few plants",IF(AND($H36<=0.1,$I36<=0.2,$J36<=0.3),"ok",TRIM(IF($H36>0.1,"SPECIES ","")&IF($I36>0.2,"GENUS ","")&IF($J36>0.3,"FAMILY","")))))
A37: =IF(Palette!$A9="","",Palette!$A9) -> Amelanchier alnifolia | B37: =IF($A37="","",Palette!$K9) -> A | C37: =IF($A37="","",Palette!$C9) -> Amelanchier | D37: =IF($A37="","",Palette!$D9) -> Rosaceae | E37: =IF($A37="","",SUMIF('Install Log'!$G$3:$G$202,$A37,'Install Log'!$J$3:$J$202)) -> 0 | F37: =IF($A37="","",SUMIF('Install Log'!$G$3:$G$202,$A37,'Install Log'!$R$3:$R$202)) -> 0 | G37: =IF(OR($A37="",N($E37)=0),"",IFERROR($F37/SUMIFS('Install Log'!$J$3:$J$202,'Install Log'!$G$3:$G$202,$A37,'Install Log'!$R$3:$R$202,"<>"),"—")) | H37: =IF(OR($A37="",$B$6=0),"",$E37/$B$6) | I37: =IF(OR($A37="",$B$6=0),"",SUMIF($C$30:$C$179,$C37,$E$30:$E$179)/$B$6) | J37: =IF(OR($A37="",$B$6=0),"",SUMIF($D$30:$D$179,$D37,$E$30:$E$179)/$B$6) | K37: =IF(OR($A37="",N($E37)=0),"",IF($B$6<'Start Here'!$B$10,"too few plants",IF(AND($H37<=0.1,$I37<=0.2,$J37<=0.3),"ok",TRIM(IF($H37>0.1,"SPECIES ","")&IF($I37>0.2,"GENUS ","")&IF($J37>0.3,"FAMILY","")))))
A38: =IF(Palette!$A10="","",Palette!$A10) -> Arbutus unedo | B38: =IF($A38="","",Palette!$K10) -> A | C38: =IF($A38="","",Palette!$C10) -> Arbutus | D38: =IF($A38="","",Palette!$D10) -> Ericaceae | E38: =IF($A38="","",SUMIF('Install Log'!$G$3:$G$202,$A38,'Install Log'!$J$3:$J$202)) -> 0 | F38: =IF($A38="","",SUMIF('Install Log'!$G$3:$G$202,$A38,'Install Log'!$R$3:$R$202)) -> 0 | G38: =IF(OR($A38="",N($E38)=0),"",IFERROR($F38/SUMIFS('Install Log'!$J$3:$J$202,'Install Log'!$G$3:$G$202,$A38,'Install Log'!$R$3:$R$202,"<>"),"—")) | H38: =IF(OR($A38="",$B$6=0),"",$E38/$B$6) | I38: =IF(OR($A38="",$B$6=0),"",SUMIF($C$30:$C$179,$C38,$E$30:$E$179)/$B$6) | J38: =IF(OR($A38="",$B$6=0),"",SUMIF($D$30:$D$179,$D38,$E$30:$E$179)/$B$6) | K38: =IF(OR($A38="",N($E38)=0),"",IF($B$6<'Start Here'!$B$10,"too few plants",IF(AND($H38<=0.1,$I38<=0.2,$J38<=0.3),"ok",TRIM(IF($H38>0.1,"SPECIES ","")&IF($I38>0.2,"GENUS ","")&IF($J38>0.3,"FAMILY","")))))
A39: =IF(Palette!$A11="","",Palette!$A11) -> Cotinus coggygria | B39: =IF($A39="","",Palette!$K11) -> A | C39: =IF($A39="","",Palette!$C11) -> Cotinus | D39: =IF($A39="","",Palette!$D11) -> Anacardiaceae | E39: =IF($A39="","",SUMIF('Install Log'!$G$3:$G$202,$A39,'Install Log'!$J$3:$J$202)) -> 0 | F39: =IF($A39="","",SUMIF('Install Log'!$G$3:$G$202,$A39,'Install Log'!$R$3:$R$202)) -> 0 | G39: =IF(OR($A39="",N($E39)=0),"",IFERROR($F39/SUMIFS('Install Log'!$J$3:$J$202,'Install Log'!$G$3:$G$202,$A39,'Install Log'!$R$3:$R$202,"<>"),"—")) | H39: =IF(OR($A39="",$B$6=0),"",$E39/$B$6) | I39: =IF(OR($A39="",$B$6=0),"",SUMIF($C$30:$C$179,$C39,$E$30:$E$179)/$B$6) | J39: =IF(OR($A39="",$B$6=0),"",SUMIF($D$30:$D$179,$D39,$E$30:$E$179)/$B$6) | K39: =IF(OR($A39="",N($E39)=0),"",IF($B$6<'Start Here'!$B$10,"too few plants",IF(AND($H39<=0.1,$I39<=0.2,$J39<=0.3),"ok",TRIM(IF($H39>0.1,"SPECIES ","")&IF($I39>0.2,"GENUS ","")&IF($J39>0.3,"FAMILY","")))))
A40: =IF(Palette!$A12="","",Palette!$A12) -> Maackia amurensis | B40: =IF($A40="","",Palette!$K12) -> A | C40: =IF($A40="","",Palette!$C12) -> Maackia | D40: =IF($A40="","",Palette!$D12) -> Fabaceae | E40: =IF($A40="","",SUMIF('Install Log'!$G$3:$G$202,$A40,'Install Log'!$J$3:$J$202)) -> 0 | F40: =IF($A40="","",SUMIF('Install Log'!$G$3:$G$202,$A40,'Install Log'!$R$3:$R$202)) -> 0 | G40: =IF(OR($A40="",N($E40)=0),"",IFERROR($F40/SUMIFS('Install Log'!$J$3:$J$202,'Install Log'!$G$3:$G$202,$A40,'Install Log'!$R$3:$R$202,"<>"),"—")) | H40: =IF(OR($A40="",$B$6=0),"",$E40/$B$6) | I40: =IF(OR($A40="",$B$6=0),"",SUMIF($C$30:$C$179,$C40,$E$30:$E$179)/$B$6) | J40: =IF(OR($A40="",$B$6=0),"",SUMIF($D$30:$D$179,$D40,$E$30:$E$179)/$B$6) | K40: =IF(OR($A40="",N($E40)=0),"",IF($B$6<'Start Here'!$B$10,"too few plants",IF(AND($H40<=0.1,$I40<=0.2,$J40<=0.3),"ok",TRIM(IF($H40>0.1,"SPECIES ","")&IF($I40>0.2,"GENUS ","")&IF($J40>0.3,"FAMILY","")))))
A41: =IF(Palette!$A13="","",Palette!$A13) -> Malus fusca | B41: =IF($A41="","",Palette!$K13) -> A | C41: =IF($A41="","",Palette!$C13) -> Malus | D41: =IF($A41="","",Palette!$D13) -> Rosaceae | E41: =IF($A41="","",SUMIF('Install Log'!$G$3:$G$202,$A41,'Install Log'!$J$3:$J$202)) -> 0 | F41: =IF($A41="","",SUMIF('Install Log'!$G$3:$G$202,$A41,'Install Log'!$R$3:$R$202)) -> 0 | G41: =IF(OR($A41="",N($E41)=0),"",IFERROR($F41/SUMIFS('Install Log'!$J$3:$J$202,'Install Log'!$G$3:$G$202,$A41,'Install Log'!$R$3:$R$202,"<>"),"—")) | H41: =IF(OR($A41="",$B$6=0),"",$E41/$B$6) | I41: =IF(OR($A41="",$B$6=0),"",SUMIF($C$30:$C$179,$C41,$E$30:$E$179)/$B$6) | J41: =IF(OR($A41="",$B$6=0),"",SUMIF($D$30:$D$179,$D41,$E$30:$E$179)/$B$6) | K41: =IF(OR($A41="",N($E41)=0),"",IF($B$6<'Start Here'!$B$10,"too few plants",IF(AND($H41<=0.1,$I41<=0.2,$J41<=0.3),"ok",TRIM(IF($H41>0.1,"SPECIES ","")&IF($I41>0.2,"GENUS ","")&IF($J41>0.3,"FAMILY","")))))
... A179: =IF(Palette!$A151="","",Palette!$A151) | B179: =IF($A179="","",Palette!$K151) | C179: =IF($A179="","",Palette!$C151) | D179: =IF($A179="","",Palette!$D151) | E179: =IF($A179="","",SUMIF('Install Log'!$G$3:$G$202,$A179,'Install Log'!$J$3:$J$202)) | F179: =IF($A179="","",SUMIF('Install Log'!$G$3:$G$202,$A179,'Install Log'!$R$3:$R$202)) | G179: =IF(OR($A179="",N($E179)=0),"",IFERROR($F179/SUMIFS('Install Log'!$J$3:$J$202,'Install Log'!$G$3:$G$202,$A179,'Install Log'!$R$3:$R$202,"<>"),"—")) | H179: =IF(OR($A179="",$B$6=0),"",$E179/$B$6) | I179: =IF(OR($A179="",$B$6=0),"",SUMIF($C$30:$C$179,$C179,$E$30:$E$179)/$B$6) | J179: =IF(OR($A179="",$B$6=0),"",SUMIF($D$30:$D$179,$D179,$E$30:$E$179)/$B$6) | K179: =IF(OR($A179="",N($E179)=0),"",IF($B$6<'Start Here'!$B$10,"too few plants",IF(AND($H179<=0.1,$I179<=0.2,$J179<=0.3),"ok",TRIM(IF($H179>0.1,"SPECIES ","")&IF($I179>0.2,"GENUS ","")&IF($J179>0.3,"FAMILY","")))))
A181: STRUCTURAL RISKS TO WATCH
A182: ="Oaks (Quercus): "&COUNTIFS(Palette!$C$2:$C$151,"Quercus",Palette!$K$2:$K$151,"A")+COUNTIFS(Palette!$C$2:$C$151,"Quercus",Palette!$K$2:$K$151,"B")&" specifiable species. Oaks lead the Group 1 clay list, so the 20% genus cap binds first on wet sites. Use Pacific crabapple and non-oak shrubs between oaks." -> Oaks (Quercus): 6 specifiable species. Oaks lead the Group 1 clay list, so the 20% genus cap binds first on wet sites. Use Pacific crabapple and non-oak shrubs between oaks.
A183: ="Rose family (Rosaceae): "&COUNTIFS(Palette!$D$2:$D$151,"Rosaceae",Palette!$K$2:$K$151,"A")+COUNTIFS(Palette!$D$2:$D$151,"Rosaceae",Palette!$K$2:$K$151,"B")&" specifiable species. Most wet-site natives are in this family, so the 30% family cap binds first in Group 1 hedgerows." -> Rose family (Rosaceae): 7 specifiable species. Most wet-site natives are in this family, so the 30% family cap binds first in Group 1 hedgerows.
A184: Replacing an ash monoculture with an oak or rose-family monoculture solves nothing.

Sheet Reference
A1: REFERENCE — RULES, SOILS AND SOURCES
A2: TIER DEFINITIONS
A3: A — Proven | B3: Documented performance in the valley. Use freely within the correct soil group.
A4: B — Trial | B4: Sound logic, unproven locally or carrying a named risk. Cap at 10% per planting. Expect higher losses.
A5: C — Caution | B5: Underperforms the low-input standard. Use only with a clear reason.
A6: Reject | B6: Do not plant. Kept in the file with the reason.
A7: Promotion rule | B7: Tier B moves to A after 3 or more installs reach year 3 with 80% or more survival. Any species with less than 70% survival is demoted. Do not count mower damage or a missed water plan.
A9: THE TWO-AXIS SCREEN
A10: Why both axes | B10: Most published drought lists rate summer water need only. Here the main killer is winter: roots sitting in saturated, low-oxygen soil November through April. Cistus, rosemary and manzanita all rate Very High on drought and Very Low on winter-wet. They survive August and die in February on Bashaw clay. Screening on drought alone produces plantings that fail in years 2–4.
A11: Rating scale | B11: Both axes use one 5-step scale: Very High, High, Moderate, Low, Very Low.
A13: WATER CLASS
A14: Standard | B14: Follows the interval table in Establishment Water for years 1-3, then no routine water.
A15: Drought-adapted | B15: 1.5x the interval in years 1-2. No summer water from year 3 on. Summer water after year 2 is a leading cause of death for these plants. Never on shared irrigation.
A17: SOIL GROUPS
A18: Group 1 — Valley bottom clay | B18: Bashaw, Dayton, Natroy, Amity, Concord, Waldo. Poorly or somewhat poorly drained, perched water table Nov–Apr. Winter-wet tolerance governs; reject Mediterranean and California upland species or plant on 12–18 in berms.
A19: Group 2 — Alluvial silt loam | B19: Malabon, Coburg, Salem, Chehalis, Newberg, Cloquato. Well to moderately well drained alluvium, mostly silt loam to silty clay loam. Most permissive — nearly the full palette.
A20: Group 3 — Footslope / upland | B20: Jory, Nekia, Bellpine, Dixonville. Well drained, droughty, moderately deep (Nekia, Bellpine, Dixonville) to very deep (Jory) over bedrock. Correct home for the California and Mediterranean species; check rooting depth before large canopy trees.
A21: Field call | B21: Pull SSURGO before the visit, then verify on site — urban parcels are routinely cut, filled or scraped, and construction fill creates Group 1 conditions on a Group 2 map unit. Auger to 24–36 in, note mottling or gley. If an 18 in hole has not drained within an hour, call it Group 1 regardless of the survey.
A23: PALETTE SUMMARY
A24: Metric | B24: Count | C24: Note
A25: Total species | B25: =COUNTA(Palette!$A$2:$A$151) -> 48 | C25: Trees and shrubs combined
A26: Tier A | B26: =COUNTIF(Palette!$K$2:$K$151,"A") -> 30 | C26: Use freely in the right soil group
A27: Tier B | B27: =COUNTIF(Palette!$K$2:$K$151,"B") -> 10 | C27: Trial only; cap per planting in Start Here
A28: Tier C or Reject | B28: =COUNTIF(Palette!$K$2:$K$151,"C")+COUNTIF(Palette!$K$2:$K$151,"Reject") -> 8 | C28: Documented exclusions
A29: Clear on Group 1 clay | B29: =COUNTIF(Palette!$L$2:$L$151,"Yes") -> 22 | C29: Hardest sites
A30: Clear on Group 2 silt loam | B30: =COUNTIF(Palette!$M$2:$M$151,"Yes") -> 32 | C30: Most permissive
A31: Clear on Group 3 upland | B31: =COUNTIF(Palette!$N$2:$N$151,"Yes") -> 28 | C31: California and Mediterranean species
A32: Drought-adapted | B32: =COUNTIF(Palette!$P$2:$P$151,"Drought-adapted") -> 8 | C32: No summer water after year 2
A33: Hard to source (4-5) | B33: =COUNTIF(Palette!$Q$2:$Q$151,">=4") -> 3 | C33: Order from a grower 2-3 years ahead
A34: Review date within 90 days | B34: =COUNTIFS(Palette!$U$2:$U$151,"<"&TODAY()+90) -> 0 | C34: Sort the Palette by Review By
A36: HOW TO USE THIS WITH EXISTING WORK
A37: Removals | B37: Plan a replacement with every removal. The equipment and access are already in place.
A38: Pruning of legacy plants | B38: Compare the 15-year cost of continued shearing with the alternative. Let the owner decide.
A39: Observed conditions | B39: Note declining birch, EAB-exposed ash and arborvitae with dead plants at each visit. No pressure to act.
A40: Succession plan | B40: Full property inventory, what fails on what horizon, and a phased 5–10 year replacement with sequencing and budget. Best for larger, commercial and public properties.
A41: Default is observation | B41: Recommend a replacement only where the plant needs it. Otherwise note it and move on. The Field Card keeps assessments consistent between people.
A42: Sequencing | B42: Observation and succession planning work today. Conversion Economics needs local shearing hours before its paybacks can be relied on.
A44: SOURCES AND CAVEATS
A45: SelecTree list 536 | B45: Source of 13 trees. Calibrated for interior California, where summer heat is the binding constraint. It does not screen winter-saturated soil, which is why several entries rate poorly here.
A46: Regional additions | B46: Natives, conifers and the wet-clay hedges are not from list 536. Added because the source list has no answer for a Group 1 screen and almost no conifers.
A47: Great Plant Picks / Xera / Cistus Nursery | B47: Regional analogs vetted for the summer-dry, winter-wet combination. Best sources for expanding the shrub layer.
A48: City of Eugene | B48: Approved Street Tree List governs right-of-way work. Ash planting on public land is under moratorium following EAB detection in Oregon.
A49: Ratings | B49: Professional judgment for this region, based on species range, native habitat and reported regional performance. Not measured trial data. Treat as a starting point and revise from the Install Log.
A50: OSU Extension EM 8721 | B50: Monnette and Hobbs, A Guide to Hedgerows (revised 2020, reviewed 2023). Source of the hedgerow design standard and of 11 wet-tolerant species. Its wet-soil list was screened for drought and invasive risk before use; six entries were rejected or limited.
A51: City of Eugene Ordinance 20351, Exhibit F | B51: Native and Non-Native Plant List. Names English laurel, sweet cherry, black locust, English ivy and English holly as invasive. Basis for the laurel considerations and two Palette rejections.
A52: OSU Solve Pest Problems: cherry laurel | B52: Describes bird-spread escape of cherry laurel into natural areas. Does not state a state noxious weed listing.
A53: ODA: Emerald Ash Borer | B53: Quarantine counties (Clackamas, Marion, Multnomah, Washington, Yamhill) and rules on ash material and hardwood firewood.
A54: Capital Press 2026-06-24; KPTV 2026-08-06 | B54: 2026 EAB detections, including Salem and Silverton. No Lane County detection reported.
A55: A.M. Leonard; Frerichs Tree Service | B55: EAB injection pricing (about $7-16 per inch DBH per treatment) and canopy-loss thresholds for treatment.

Sheet Lists
A1: Tolerance | B1: Tier | C1: Site Fit | D1: Soil Group | E1: Condition | F1: Water Class | G1: Water By | H1: Failure Cause | I1: Class | J1: Ash Value | K1: Ash Site | L1: Y/N | M1: Ash Action
A2: Very High | B2: A | C2: Yes | D2: 1 | E2: 5 | F2: Standard | G2: Owner | H2: Drought | I2: Remove soon | J2: High | K2: Upland | L2: Y | M2: Monitoring
A3: High | B3: B | C3: Caution | D3: 2 | E3: 4 | F3: Drought-adapted | G3: Contractor | H3: Winter-wet / root rot | I3: Optional | J3: Medium | K3: Wet | L3: N | M3: Treated
A4: Moderate | B4: C | C4: No | D4: 3 | E4: 3 | H4: Heat event | I4: Plan succession | J4: Low | K4: Riparian | M4: Successor planted
A5: Low | B5: Reject | E5: 2 | H5: Deer or rodent | M5: Removed and replaced
A6: Very Low | E6: 1 | H6: Pest or disease | M6: Removed only
H7: Mechanical (mower, trimmer) | M7: Owner declined
H8: Transplant shock
H9: Water plan not followed
H10: Unknown
